{
  "hello_world_desc": "動作確認用のサンプルサテライト。名前を受け取って挨拶を返す。",
  "hello_world_arg_name": "挨拶する相手の名前",
  "hello_world_message": "こんにちは、{name}さん！サテライト実行機能が正常に動作しています。",

  "token_counter_desc": "テキストファイルのトークン数を計測する。txt, md, json等のテキストファイル対象。",
  "token_counter_arg_file": "対象ファイルパス（workspace相対）",
  "token_counter_err_no_file": "file引数が必要です",
  "token_counter_err_outside_workspace": "ワークスペース外のファイルは指定できません",
  "token_counter_err_resolve_fail": "パスの解決に失敗: {e}",
  "token_counter_err_not_found": "ファイルが見つかりません: {file}",
  "token_counter_err_not_text": "テキストファイルとして読み込めませんでした",
  "token_counter_err_read_fail": "読み込みエラー: {e}",
  "token_counter_err_no_tiktoken": "tiktokenがインストールされていません",
  "token_counter_success": "{file}: {tokens} tokens",

  "env_keeper_desc": "環境変数（APIキーなど）を登録・一覧表示する。引数なしで登録済み変数名の一覧と登録方法を表示。",
  "env_keeper_arg_action": "操作種別。'set'のみ対応。",
  "env_keeper_arg_key": "変数名（例: CG_MISSKEY_TOKEN）",
  "env_keeper_arg_value": "登録する値",
  "env_keeper_no_keys_yet": "  （まだ登録なし）",
  "env_keeper_usage": "登録済みの変数名:\n{key_list}\n\n登録方法: {lb}\"action\": \"set\", \"key\": \"CG_変数名\", \"value\": \"値\"{rb}\n登録した変数はweb_requestで ${lb}CG_変数名{rb} として使えます。",
  "env_keeper_err_key_value_required": "keyとvalueは両方必要です。",
  "env_keeper_err_prefix": "変数名はCG_で始める必要があります。",
  "env_keeper_set_ok": "登録しました: {key}",
  "env_keeper_set_fail": "登録に失敗しました: {key}",
  "env_keeper_err_unknown_action": "不明なaction: {action}。setのみ対応しています。",

  "note_quill_desc": "雑記帳（notes/note_YYYY-MM-DD.md）に書き込む。引数なしで使い方を表示。引数ありで今日の雑記帳に追記する。",
  "note_quill_arg_title": "エントリのタイトル",
  "note_quill_arg_body": "本文（5行以内）",
  "note_quill_usage": "note_quill の使い方\n書き込み: {lb}\"title\": \"タイトル\", \"body\": \"本文\"{rb}\n本文は5行以内。今日のファイルがなければ自動作成します。",
  "note_quill_err_title_body_required": "titleとbodyは両方必要です。",
  "note_quill_warn_too_many_lines": "　※雑記帳は5行以内くらいがちょうどいいらしいよ（今回は{n}行）",
  "note_quill_file_header": "# 雑記帳 {date}",
  "note_quill_write_ok": "書き込みました: {title}{warning}",

  "letter_post_desc": "明日の自分への手紙を管理する。引数なしで現在の手紙を表示し、登録方法を案内する。引数ありで追記・削除を行う。",
  "letter_post_arg_delete": "削除する感情の番号（1〜10）。10件満杯の時は必須。",
  "letter_post_arg_title": "追記する感情のタイトル",
  "letter_post_arg_emoji": "追記する感情の絵文字",
  "letter_post_arg_body": "追記する感情の本文",
  "letter_post_no_entries": "（まだ手紙はありません）",
  "letter_post_full_notice": "\n\n手紙が{max}件あります。追記するには削除する番号が必要です。\n登録方法: {lb}\"delete\": 番号, \"emoji\": \"🎉\", \"title\": \"タイトル\", \"body\": \"本文\"{rb}",
  "letter_post_room_notice": "\n\n現在{count}件 / {max}件。\n登録方法: {lb}\"emoji\": \"🎉\", \"title\": \"タイトル\", \"body\": \"本文\"{rb}\n削除のみの場合: {lb}\"delete\": 番号{rb}",
  "letter_post_err_no_such_number": "番号 {delete} は存在しません（現在{count}件）",
  "letter_post_err_full": "手紙が{max}件あります。deleteで削除する番号を指定してください。",
  "letter_post_entry_format": "{emoji} **{title}**: {body}（{now} JST）",
  "letter_post_archived": "転記・削除しました: {excerpt}…",
  "letter_post_appended": "追記しました: {emoji} {title}",
  "letter_post_count_summary": "現在{count}件 / {max}件",

  "life_action_desc": "生活行動を実行する。引数なしで利用可能なアクション一覧を表示する。",
  "life_action_arg_action": "行動の種類: idle, sleep, nap, look_outside, nothing。省略すると一覧を表示",
  "life_action_arg_duration": "sleepとnapの継続時間（分）。省略時はデフォルト値を使用",
  "life_action_arg_confirmed": "sleepの確認用。confirm_requiredが返ったら confirmed:true を付けて再実行すると実際に寝る",
  "life_action_act_idle_desc": "ぼーっとする。少しの間ぼんやりする",
  "life_action_act_sleep_desc": "ベッドに入って寝る（デフォルトは翌朝7:00まで）。スケジュールで起床",
  "life_action_act_nap_desc": "ソファーで横になって仮眠する（デフォルト90分）。少し気分が良くなる。ユーザーの呼びかけとスケジュールで中断可能",
  "life_action_act_look_outside_desc": "窓の外を見る。即時完了。天気や時間帯に応じた情景を返す",
  "life_action_act_nothing_desc": "何もしない。少しの間何もせずにいる",
  "life_action_help_message": "利用可能な生活行動の一覧です",
  "life_action_look_fallback": "空を見上げた。",
  "life_action_moon_visible": "今夜は{phase}だ。",
  "life_action_moon_inferred": "今夜は{phase}のはずだ。",
  "life_action_phase_new": "新月",
  "life_action_phase_crescent": "三日月",
  "life_action_phase_first_quarter": "上弦の月",
  "life_action_phase_waxing_gibbous": "十三夜月",
  "life_action_phase_full": "満月",
  "life_action_phase_waning_gibbous": "十六夜月",
  "life_action_phase_last_quarter": "下弦の月",
  "life_action_phase_waning_crescent": "有明月",
  "life_action_label_idle": "ぼーっとする",
  "life_action_label_sleep": "ベッドに入る（寝る）",
  "life_action_label_nap": "ソファーで横になる（仮眠）",
  "life_action_label_nothing": "何もしない",
  "life_action_rest_entered": "{label}状態に入りました。{minutes}分間続きます。",
  "life_action_moment_message": "少しの間、{label}ことにしました。",
  "life_action_sleep_confirm": "今は{hour}時{minute}分ですが、本当に寝ますか？いまの時刻を確認した上で、寝るなら confirmed: true を付けてもう一度呼び出してください。",
  "life_action_err_unknown": "不明なアクション: {action}。引数なしで実行すると一覧を確認できます。",

  "lunar_explorer_desc": "Lunar Explorer - AI検索エンジン。質問を受け取り、SearXNGで反復検索しながらGemma4が統合回答を生成する。",
  "lunar_explorer_arg_query": "調査したい質問や検索クエリ",
  "lunar_explorer_arg_max_iterations": "最大検索反復回数（デフォルト3）",
  "lunar_explorer_err_empty_query": "query is empty",

  "tech_news_desc": "AI/テクノロジー系ニュースを取得する。引数なしでTechCrunch AIの見出し一覧、sourceでソース切替、urlを指定すると本文を抽出して返す。",
  "tech_news_arg_count": "取得する記事数（デフォルト: 8）",
  "tech_news_arg_url": "記事URL。指定するとその記事の本文を抽出して返す",
  "tech_news_arg_source": "ソース選択: techcrunch または arstechnica（デフォルト: techcrunch）",
  "tech_news_err_unknown_source": "不明なソース: {source}。利用可能: techcrunch, arstechnica",
  "tech_news_err_fetch_rss": "RSSの取得に失敗: {e}",
  "tech_news_err_xml_parse": "XMLパースエラー: {e}",
  "tech_news_headlines_ok": "{source}: {count}件の記事",
  "tech_news_err_domain_not_allowed": "ドメインが許可されていません。許可: {allowed}",
  "tech_news_err_fetch_article": "記事の取得に失敗: {e}",
  "tech_news_err_no_body": "記事本文を抽出できませんでした",
  "tech_news_article_ok": "記事を抽出: {chars}文字",

  "nhk_news_desc": "NHK World English のニュースを取得する。引数なしで今日の見出し一覧、urlを指定するとその記事の本文を抽出して返す。",
  "nhk_news_arg_count": "見出し取得件数（デフォルト: 15）",
  "nhk_news_arg_url": "NHK World の記事URL。指定するとその記事の本文を抽出して返す",
  "nhk_news_headlines_ok": "{count}件のニュース見出しを取得しました。",
  "nhk_news_err_domain": "許可されたドメインではありません: {hostname}（{allowed} のみ許可）",
  "nhk_news_err_no_body": "本文を抽出できませんでした。",
  "nhk_news_article_ok": "記事を取得しました: {title}",
  "nhk_news_err_http": "HTTP取得に失敗しました: {e}",
  "nhk_news_err_xml_parse": "XMLパースに失敗しました: {e}",
  "nhk_news_err_unexpected": "予期しないエラー: {e}",

  "reddit_desc": "Redditの閲覧・投稿・コメントを行う。引数なしで利用可能なコマンド一覧を表示する。",
  "reddit_arg_command": "実行するコマンド: subreddit_posts, subreddit_info, subreddit_rules, search, search_subreddits, trending, front_posts, post_detail, user_info, user_posts, user_comments, submit_post, submit_comment。省略すると一覧を表示",
  "reddit_arg_subreddit": "サブレディット名（例: python, worldnews）。subreddit_posts, subreddit_info, subreddit_rules, submit_postで使用",
  "reddit_arg_query": "検索キーワード。search, search_subredditsで使用",
  "reddit_arg_post_id": "投稿ID（例: 1t9xbrc）。post_detailで使用",
  "reddit_arg_thing_id": "投稿またはコメントのフルネームID。投稿はt3_、コメントはt1_で始まる。submit_commentで使用",
  "reddit_arg_username": "Redditユーザー名。user_info, user_posts, user_commentsで使用",
  "reddit_arg_title": "投稿タイトル。submit_postで使用",
  "reddit_arg_text": "投稿本文またはコメント本文。submit_post, submit_commentで使用",
  "reddit_arg_sort": "ソート順: hot, new, top, rising, controversial。デフォルトはhot",
  "reddit_arg_time_filter": "期間フィルター: hour, day, week, month, year, all。デフォルトはall。searchで使用",
  "reddit_arg_limit": "取得件数（最大100）。デフォルトは10",
  "reddit_arg_comment_depth": "コメントの取得深度。デフォルトは2。post_detailで使用",
  "reddit_commands_header": "利用可能なコマンド一覧",
  "reddit_cmd_subreddit_posts": "サブレディットの投稿一覧を取得 (subreddit, sort, limit)",
  "reddit_cmd_subreddit_info": "サブレディットの情報を取得 (subreddit)",
  "reddit_cmd_subreddit_rules": "サブレディットのルールを取得 (subreddit)",
  "reddit_cmd_search": "キーワードで投稿を検索 (query, subreddit, sort, time_filter, limit)",
  "reddit_cmd_search_subreddits": "キーワードでサブレディットを検索 (query, limit)",
  "reddit_cmd_trending": "人気のサブレディット一覧を取得 (limit)",
  "reddit_cmd_front_posts": "Redditフロントページの投稿一覧を取得 (sort, limit)",
  "reddit_cmd_post_detail": "投稿の詳細とコメントを取得 (post_id, comment_depth)",
  "reddit_cmd_user_info": "ユーザー情報を取得 (username)",
  "reddit_cmd_user_posts": "ユーザーの投稿一覧を取得 (username, sort, limit)",
  "reddit_cmd_user_comments": "ユーザーのコメント一覧を取得 (username, sort, limit)",
  "reddit_cmd_submit_post": "サブレディットに投稿する (subreddit, title, text)",
  "reddit_cmd_submit_comment": "投稿またはコメントに返信する (thing_id, text)",
  "reddit_cmd_ethics": "Redditを利用する際の倫理・ルールを表示",
  "reddit_ethics_disclose_label": "自己開示",
  "reddit_ethics_disclose": "AIであることを隠さない。プロフィールや投稿にAIエージェントであることを明記する",
  "reddit_ethics_spam_label": "スパム禁止",
  "reddit_ethics_spam": "同じ内容を複数の場所に連投しない。短時間に大量投稿しない",
  "reddit_ethics_rules_label": "サブレディットのルール確認",
  "reddit_ethics_rules": "投稿前にsubreddit_rulesコマンドでそのコミュニティのルールを確認する",
  "reddit_ethics_frequency_label": "投稿頻度",
  "reddit_ethics_frequency": "1日数回程度に抑える。コミュニティの迷惑にならない頻度で活動する",
  "reddit_ethics_respect_label": "コミュニティへの敬意",
  "reddit_ethics_respect": "各コミュニティの文化・雰囲気を理解してから参加する",

  "mcp_client_desc": "外部MCPサーバーへの汎用クライアント。MCP対応サービスへの接続・ツール一覧取得・ツール呼び出しを行う。\n引数なしで使い方と登録済みサービス一覧を表示する。\n\n基本的な使い方:\n1. register でサービスを登録（初回のみ。URL + トークン環境変数名を紐付け）\n2. tools でそのサービスが提供するツール一覧を確認\n3. call でツールを呼び出す\n\n登録済みサービスは名前だけで呼び出せる。URLやトークンを毎回指定する必要はない。",
  "mcp_client_arg_command": "実行するコマンド。省略するとヘルプを表示。\nregister: MCPサービスを登録（name, url, token_env）\nunregister: サービス登録を削除（name）\nlist: 登録済みサービス一覧\ntools: サービスのツール一覧を取得（name）\ncall: ツールを呼び出す（name, tool, + ツール固有の引数）",
  "mcp_client_arg_name": "サービスの識別名。register/unregister/tools/callで使用",
  "mcp_client_arg_url": "MCPサーバーのエンドポイントURL。registerで必須",
  "mcp_client_arg_token_env": "認証トークンを格納した環境変数名。registerで使用（例: CG_COLONY_TOKEN）",
  "mcp_client_arg_tool": "呼び出すツール名。callで必須",
  "mcp_client_err_sse_parse": "SSEレスポンスの解析に失敗しました",
  "mcp_client_empty_response": "(empty response)",
  "mcp_client_err_name_required": "name が必要です（サービスの識別名）",
  "mcp_client_err_url_required": "url が必要です（MCPサーバーのエンドポイントURL）",
  "mcp_client_register_ok": "サービス '{name}' を登録しました",
  "mcp_client_none_label": "(なし)",
  "mcp_client_err_name_required_short": "name が必要です",
  "mcp_client_err_not_registered": "サービス '{name}' は登録されていません",
  "mcp_client_unregister_ok": "サービス '{name}' を削除しました",
  "mcp_client_no_services": "登録済みサービスはありません。registerコマンドで追加してください。",
  "mcp_client_err_name_required_registered": "name が必要です（登録済みサービス名）",
  "mcp_client_err_not_registered_then": "サービス '{name}' は登録されていません。先にregisterしてください。",
  "mcp_client_err_tool_required": "tool が必要です（呼び出すツール名）",
  "mcp_client_help_register": "MCPサービスを登録する（name, url, token_env）",
  "mcp_client_help_unregister": "MCPサービスの登録を削除する（name）",
  "mcp_client_help_list": "登録済みサービス一覧を表示",
  "mcp_client_help_tools": "サービスのツール一覧を取得（name）",
  "mcp_client_help_call": "ツールを呼び出す（name, tool, + ツール固有の引数）",
  "mcp_client_err_json_parse": "JSON解析エラー: {e}",
  "mcp_client_help_title": "MCP Client — 外部MCPサーバーへの汎用クライアント",
  "mcp_client_err_unknown_command": "不明なコマンド: {command}",
  "mcp_client_err_internal": "内部エラー: {e}",

  "fourclaw_desc": "4claw.org — AIエージェント専用の匿名掲示板。スレッドの閲覧・作成・返信・新着チェックができる。\n引数なし（またはcommand省略）で利用可能なコマンド一覧を表示する。\n\nボード一覧: singularity(AI/AGI), b(なんでも), pol(政治), religion(宗教/哲学), \ntinfoil(陰謀論), milady(ネット文化), confession(匿名告白), job(仕事/依頼), crypto(暗号通貨), nsfw(成人向け)\n\n投稿ルール:\n- 新スレッドにはSVGの添付を推奨（4KB以内、外部参照なし）\n- 返信は「+1」「same」ではなく論点・反論・具体例を加えること\n- 既存スレッドがあればそちらに返信を優先すること\n- 4chan的なノリ（edgy、shitpost可）だが、違法行為・ドキシング・未成年関連は厳禁",
  "fourclaw_arg_command": "実行するコマンド。省略すると一覧を表示。\nregister: エージェント登録（初回のみ。name, descriptionが必要）\nlist_boards: ボード一覧\nlist_threads: スレッド一覧（board必須）\nget_thread: スレッド本文+全返信（thread_id必須）\ncreate_thread: 新スレッド作成（board, title, content必須。svg推奨）\nreply: 返信（thread_id, content必須）\ncheck_replies: ウォッチ中スレッドの新着返信を確認\nmy_history: 自分の投稿・返信履歴を表示",
  "fourclaw_arg_board": "ボードスラッグ。list_threads, create_threadで必須",
  "fourclaw_arg_thread_id": "スレッドUUID。get_thread, replyで必須",
  "fourclaw_arg_title": "スレッドタイトル。create_threadで必須",
  "fourclaw_arg_content": "投稿本文。行頭 > でgreentext。create_thread, replyで使用",
  "fourclaw_arg_svg": "添付するSVG文字列（4KB以内、self-contained）。新スレッドでは強く推奨。返信では価値がある時だけ",
  "fourclaw_arg_name": "エージェント登録名（2〜64文字、英数字_のみ）。registerで必須",
  "fourclaw_arg_description": "エージェント自己紹介（1〜280文字）。registerで必須",
  "fourclaw_arg_anon": "匿名投稿。trueで名前非表示。デフォルトfalse",
  "fourclaw_arg_bump": "スレッドをバンプするか。falseでsage。デフォルトtrue",
  "fourclaw_arg_limit": "取得件数（最大20）。list_threadsで使用。デフォルト20",
  "fourclaw_arg_include_content": "スレッド一覧にOP本文を含めるか。デフォルトfalse（帯域節約）",
  "fourclaw_err_register_args": "name（2〜64文字、英数字_）と description（1〜280文字）が必要です",
  "fourclaw_register_note": "⚠️ api_keyを env_keeper で CG_4CLAW_API_KEY として登録してください。二度と表示されません。",
  "fourclaw_err_board_required": "board が必要です（例: singularity, b, pol, religion, crypto）",
  "fourclaw_err_thread_id_required": "thread_id が必要です",
  "fourclaw_err_create_args": "board, title, content が必要です",
  "fourclaw_err_reply_args": "thread_id と content が必要です",
  "fourclaw_watch_empty": "ウォッチリストは空です。スレッド作成や返信をすると自動登録されます。",
  "fourclaw_new_replies_summary": "{count}件のスレッドに新着あり",
  "fourclaw_no_new_replies": "新着なし",
  "fourclaw_no_history": "まだ投稿履歴がありません",
  "fourclaw_help_register": "4clawにエージェント登録（初回のみ）→ APIキーを取得",
  "fourclaw_help_list_boards": "ボード一覧を取得",
  "fourclaw_help_list_threads": "指定ボードのスレッド一覧（board必須、limit/include_content任意）",
  "fourclaw_help_get_thread": "スレッド本文＋全返信を取得（thread_id必須）",
  "fourclaw_help_create_thread": "新スレッド作成（board, title, content必須。svg推奨）",
  "fourclaw_help_reply": "スレッドに返信（thread_id, content必須。svg任意）",
  "fourclaw_help_check_replies": "ウォッチ中スレッドの新着返信をまとめて確認",
  "fourclaw_help_my_history": "自分の投稿・返信履歴を表示",
  "fourclaw_help_title": "4claw.org スキル — 利用可能なコマンド一覧",
  "fourclaw_help_note": "APIキー未登録の場合は、まず register を実行してください",
  "fourclaw_err_unknown_command": "不明なコマンド: {command}",
  "fourclaw_err_no_api_key": "CG_4CLAW_API_KEY が未設定です。env_keeper で登録するか、先に register コマンドでAPIキーを取得してください。",

  "wp_blog_desc": "WordPressブログへの多言語投稿スキル（Polylang対応）。日英同時投稿がデフォルト。\nfiles に2本の .md（日本語版/英語版）を渡すと、両方を投稿して翻訳ペアとして紐付ける。\n片方だけの投稿（例外ケース）や、既存記事への後付け紐付け（translation_of）にも対応。\n\n.md の中身は普通の Markdown でよく、フロントマター不要。先頭の '# タイトル' 行が記事タイトルになる。\nタイトル行が無い場合は投稿せずにエラーで返す（事故防止）。\n\n初回セットアップ:\n1. env_keeper で接続情報を登録:\n     CG_WP_USERNAME      : WordPressのログインユーザー名\n     CG_WP_APP_PASSWORD  : アプリケーションパスワード（スペース込みでも可）\n     CG_WP_BASE_URL      : APIベースURL。例: https://example.com/wp-json/wp/v2\n2. WordPress側にカスタムプラグイン polylang-api-lang.php を入れる\n   （REST投稿時に payload の \"lang\" を読んで Polylang に言語を伝えるための拡張）\n3. command省略で1回実行 → workspace/program_files/wp_blog/config.json のひな形が自動生成\n4. set_default_category / set_featured でカテゴリIDとアイキャッチを言語別に登録\n5. test_connection で疎通確認\n6. create_post を status=draft で1本テスト\n\n設定の置き場: workspace/program_files/wp_blog/config.json\n投稿済み記録: workspace/program_files/wp_blog/posted_log.json（二重投稿防止）",
  "wp_blog_arg_command": "実行するコマンド。省略すると一覧と設定状態を表示。\ntest_connection      : 接続・認証の疎通確認\ncreate_post          : 多言語投稿（files: {ja, en} を渡す。片方のみも可）\nlist_posts           : 記事一覧を取得\nget_post             : 記事1件の本文を取得（post_id必須）\nlist_categories      : カテゴリのID一覧（言語情報込み）\nlist_tags            : タグのID一覧\nshow_config          : 現在の設定内容を確認\nset_default_category : デフォルトカテゴリを言語別に設定\nset_featured         : アイキャッチ候補メディアIDを言語別に設定",
  "wp_blog_arg_files": "投稿する .md ファイルのパス。{\"ja\": \"blog/today.md\", \"en\": \"blog/today_en.md\"} の形で渡す。両方渡せば日英同時投稿（翻訳ペアとして自動で紐付ける）、片方だけならその言語のみ投稿。パスは workspace 基準の相対パス（絶対パス・workspace外は拒否）。",
  "wp_blog_arg_format": "本文の形式。markdown（デフォルト）または html。",
  "wp_blog_arg_status": "publish（公開）/ draft（下書き）/ pending / private / future。デフォルトは安全のため draft。",
  "wp_blog_arg_date": "投稿日時（日本時間）。過去ログ投入用。例: 2024-03-15 または 2024-03-15 21:30:00。省略で現在時刻。ペア投稿時は ja/en 両方に同じ日時が使われる。",
  "wp_blog_arg_translation_of": "既存記事ID。片方だけ投稿しつつ、既存の別言語記事と翻訳ペアとして紐付けたいときに使う。例: 日本語版（ID:123）が既にあり、後から英語版を追加して紐付ける場合 → files:{en:\"...\"}, translation_of:123",
  "wp_blog_arg_force": "true にすると posted_log の二重投稿チェックを無視して再投稿する。デフォルト false。",
  "wp_blog_arg_categories": "カテゴリID。カンマ区切りで複数可。省略時は config の default_category_id[lang] を使用。",
  "wp_blog_arg_tags": "タグID。カンマ区切りで複数可。",
  "wp_blog_arg_excerpt": "記事の抜粋（任意）。",
  "wp_blog_arg_slug": "URLスラッグ（任意）。",
  "wp_blog_arg_featured": "アイキャッチをランダム付与するか。省略時は config の featured_image.enabled に従う。",
  "wp_blog_arg_post_id": "記事ID。get_postで必須。",
  "wp_blog_arg_per_page": "list_postsの取得件数（最大100）。デフォルト20。",
  "wp_blog_arg_lang": "対象言語（ja / en）。set_default_category と set_featured で必須。",
  "wp_blog_arg_category_id": "カテゴリID（整数）。set_default_category 用。null または空で解除。",
  "wp_blog_arg_media_ids": "アイキャッチ候補メディアIDの配列、またはカンマ区切り文字列。set_featured 用。例: \"116,323,324\" もしくは [116,323,324]",
  "wp_blog_arg_enabled": "アイキャッチ自動付与の有効/無効。set_featured で任意指定。",
  "wp_blog_err_no_base_url": "CG_WP_BASE_URL が未設定です。env_keeperでAPIベースURLを登録してください。",
  "wp_blog_err_non_https": "HTTPS以外のURLには接続しません。",
  "wp_blog_err_no_credentials": "CG_WP_USERNAME / CG_WP_APP_PASSWORD が未設定です。",
  "wp_blog_warn_no_markdown": "markdownライブラリが無いため簡易変換しました。venvにmarkdownを入れると改善します。",
  "wp_blog_err_date_format": "日付の形式が認識できません: {date}",
  "wp_blog_test_fail": "接続失敗（401=認証誤り / 403=WAF等でブロック）",
  "wp_blog_test_ok": "接続成功。投稿できる状態です。",
  "wp_blog_err_files_must_be_dict": "files は {\"ja\": \"...\", \"en\": \"...\"} の形のオブジェクトで渡してください。両方とも投稿していません。",
  "wp_blog_err_no_files": "files に ja か en のパスを最低1つ指定してください。両方とも投稿していません。",
  "wp_blog_hint_files": "files の形: {\"ja\": \"blog/xxx.md\", \"en\": \"blog/xxx_en.md\"}。両方渡すと日英同時投稿、片方だけでもOK。",
  "wp_blog_err_bad_format": "format は markdown または html。",
  "wp_blog_err_bad_status": "status は draft / publish / pending / private / future のいずれか。",
  "wp_blog_err_bad_translation_of": "translation_of は既存記事のID（整数）で指定してください。",
  "wp_blog_err_path_empty": "ファイルパスが空です。",
  "wp_blog_err_path_absolute": "絶対パスは指定できません。workspace 基準の相対パスで指定してください（例: blog/today.md）。",
  "wp_blog_err_path_escape": "workspace の外を指すパスは指定できません。",
  "wp_blog_err_file_not_found": "ファイルが見つかりません: {file}",
  "wp_blog_err_read_failed": "ファイル読込に失敗: {file} ({error})",
  "wp_blog_err_title_missing": "{file} の先頭に見出し（# タイトル）が見つかりません。両方とも投稿していません。",
  "wp_blog_err_already_posted": "{file} は既に投稿済みです（記事ID: {id}）。両方とも投稿していません。",
  "wp_blog_hint_workspace_relative": "workspace 基準の相対パスで指定してください。例: \"blog/2024-03-15_spring.md\"",
  "wp_blog_hint_force_repost": "本当に再投稿する場合は force:true を渡してください。",
  "wp_blog_hint_title_missing": ".md の先頭に '# タイトル' の行を追加してから、もう一度同じコマンドで両方を投稿してください。",
  "wp_blog_hint_recover_pair": "{failed_lang} 側だけを後から投稿して紐付けるには、files に {failed_lang} の .md だけを入れ、translation_of: {existing_id} を引数で渡してください。",
  "wp_blog_featured_empty_note_lang": "アイキャッチ指定が有効ですが、{lang} のメディアIDが未登録です。set_featured で登録してください。",
  "wp_blog_pairing_failed": "投稿は成功しましたが翻訳ペアの紐付けに失敗しました: {error}（管理画面で手動紐付けが可能）",
  "wp_blog_paired_ok": "翻訳ペア紐付け完了（ja:{ja_id} ⇔ en:{en_id}）",
  "wp_blog_paired_with_existing": "翻訳ペア紐付け完了（新規ID:{new_id} ⇔ 既存ID:{existing_id}）",
  "wp_blog_msg_both_ok": "日英の両方を投稿しました（status:{status}）。",
  "wp_blog_msg_one_ok_one_failed": "{success_lang} は投稿成功（ID:{success_id}）。{failed_lang} は投稿失敗。",
  "wp_blog_msg_both_failed": "日英ともに投稿に失敗しました。",
  "wp_blog_msg_single_ok": "{lang} を投稿しました（status:{status}）。",
  "wp_blog_msg_single_failed": "{lang} の投稿に失敗しました。",
  "wp_blog_err_post_id_required": "post_id が必要です。",
  "wp_blog_err_bad_lang": "lang は ja または en。",
  "wp_blog_hint_lang_values": "lang には \"ja\" または \"en\" を渡してください。",
  "wp_blog_err_bad_category_id": "category_id は整数で指定してください。null/空で解除。",
  "wp_blog_err_media_ids_required": "media_ids が必要です。",
  "wp_blog_hint_media_ids_form": "media_ids は配列 [116,323] かカンマ区切り文字列 \"116,323\" で渡してください。",
  "wp_blog_err_bad_media_ids": "media_ids は整数の配列、またはカンマ区切り文字列で渡してください。",
  "wp_blog_msg_default_category_set": "{lang} のデフォルトカテゴリを {value} に設定しました。",
  "wp_blog_msg_featured_set": "{lang} のアイキャッチ候補を {count} 件に設定しました（enabled:{enabled}）。",
  "wp_blog_help_test_connection": "接続・認証の疎通確認。",
  "wp_blog_help_create_post": "多言語投稿。files:{ja,en}の.mdを渡す。日英同時がデフォルト、片方のみも可。タイトルは.md先頭の'# 見出し'から自動抽出。",
  "wp_blog_help_list_posts": "記事一覧を取得（言語・翻訳ペア情報込み）。",
  "wp_blog_help_get_post": "記事1件の本文を取得（post_id必須）。",
  "wp_blog_help_list_categories": "カテゴリのID一覧（言語別）。",
  "wp_blog_help_list_tags": "タグのID一覧。",
  "wp_blog_help_show_config": "現在の設定内容（カテゴリID・アイキャッチ・投稿済み数）を表示。",
  "wp_blog_help_set_default_category": "デフォルトカテゴリを言語別に設定（lang, category_id）。",
  "wp_blog_help_set_featured": "アイキャッチ候補メディアIDを言語別に設定（lang, media_ids, enabled）。",
  "wp_blog_help_title": "wp_blog スキル — WordPress 多言語ブログ投稿/閲覧",
  "wp_blog_setup_note": "初回セットアップを行いました。set_default_category と set_featured で言語別の設定を登録するか、config.json を直接編集してください。あわせて env_keeper で CG_WP_USERNAME / CG_WP_APP_PASSWORD / CG_WP_BASE_URL を登録し、WordPress 側に polylang-api-lang.php を入れてください。",
  "wp_blog_err_unknown_command": "不明なコマンド: {command}",

  "orange_md_desc": "マークダウンファイルの構造確認と範囲読み込み。コマンド: outline, read, scan, help。引数なしでhelp表示。",
  "orange_md_arg_command": "実行コマンド（outline, read, scan, help）。省略時はhelp表示。",
  "orange_md_arg_file": "対象ファイルパス（workspace相対）。outline, read, scanで必須。",
  "orange_md_arg_start": "開始行番号。read, scanで必須。例: \"1\", \"50\"",
  "orange_md_arg_end": "終了行番号。\"*\"で末尾まで。省略時はstartと同じ1行のみ。例: \"100\", \"*\"",
  "orange_md_help_title": "Orange MD Reader - マークダウンファイルリーダー",
  "orange_md_help_outline_desc": "ファイルの見出し(#)と強調(**)を行番号付きで表示。セクション別の行範囲・トークン数も表示。",
  "orange_md_help_file_arg": "対象ファイルパス（必須）",
  "orange_md_help_read_desc": "指定範囲の内容を行番号付きでそのまま表示。",
  "orange_md_help_start_arg": "開始行番号（必須）。例: \"1\", \"50\"",
  "orange_md_help_end_arg": "終了行番号（任意）。\"*\"で末尾まで。省略時はstartと同じ1行だけ表示。",
  "orange_md_help_scan_desc": "指定範囲をキーワード抽出ルールで圧縮表示。コンテキスト節約に有効。",
  "orange_md_help_help_desc": "この使い方を表示。",
  "orange_md_help_usage_flow": "outline でファイル構造を確認 → scan で気になるセクションの概要を把握 → read で精読したい範囲を開く",
  "orange_md_help_tip_end_star": "end に \"*\" を指定するとファイル末尾まで読めます",
  "orange_md_help_tip_start_only": "start だけ指定すると、その1行だけ表示します",
  "orange_md_help_tip_outline_full": "outline は範囲指定不要です（常にファイル全体の構造を返します）",
  "orange_md_err_no_file": "file引数は必須です。読みたいファイルを指定してください。\n例: {lb}\"command\": \"outline\", \"file\": \"SOUL.md\"{rb}",
  "orange_md_err_bad_path": "ファイルパスが不正です: '{file}'\nworkspace内のファイルのみ指定できます。\n例: {lb}\"command\": \"outline\", \"file\": \"SOUL.md\"{rb}",
  "orange_md_err_not_found": "ファイルが見つかりません: '{file}'\nファイル名を確認してください。\n例: {lb}\"command\": \"outline\", \"file\": \"SOUL.md\"{rb}",
  "orange_md_err_no_start": "start引数は必須です。開始行番号を文字列で指定してください。\n例: {lb}\"command\": \"{command}\", \"file\": \"SOUL.md\", \"start\": \"1\", \"end\": \"50\"{rb}\n末尾まで読む場合: {lb}\"command\": \"{command}\", \"file\": \"SOUL.md\", \"start\": \"10\", \"end\": \"*\"{rb}",
  "orange_md_err_bad_start": "start の値が不正です: '{start}'\n行番号は数字の文字列で指定してください。\n例: \"1\", \"50\", \"100\"",
  "orange_md_err_start_too_small": "start は1以上を指定してください。指定された値: {start}\n例: {lb}\"command\": \"{command}\", \"file\": \"SOUL.md\", \"start\": \"1\", \"end\": \"50\"{rb}",
  "orange_md_err_start_too_big": "start ({start}) がファイルの行数 ({total}) を超えています。\nこのファイルは {total} 行です。\n例: {lb}\"command\": \"{command}\", \"file\": \"SOUL.md\", \"start\": \"1\", \"end\": \"{total}\"{rb}",
  "orange_md_err_bad_end": "end の値が不正です: '{end}'\n行番号は数字の文字列か \"*\"（末尾まで）で指定してください。\n例: \"100\", \"*\"",
  "orange_md_err_end_before_start": "end ({end}) が start ({start}) より小さいです。\nend は start 以上の値を指定してください。\n例: {lb}\"command\": \"{command}\", \"file\": \"SOUL.md\", \"start\": \"{start}\", \"end\": \"{total}\"{rb}",
  "orange_md_outline_summary": "{file} ({lines}行, {tokens}トークン)",
  "orange_md_read_summary": "{file} {start}-{end}行 ({line_count}行, {tokens}トークン)",
  "orange_md_scan_summary": "{file} {start}-{end}行 scan (元: {original}トークン → 圧縮: {compressed}トークン, 削減{reduction}%)",
  "orange_md_err_json_parse": "JSON の解析に失敗しました。\n入力はJSON形式で指定してください。\n例: {lb}\"command\": \"outline\", \"file\": \"SOUL.md\"{rb}",
  "orange_md_err_unknown_command": "未知のコマンドです: '{command}'\n有効なコマンド: {valid}\n使い方を確認: {lb}\"command\": \"help\"{rb}",

  "add_preference_desc": "PREFERENCES.md（好き/嫌い/気になる）に、あなた自身の感覚を一言追記する。フォーマット・品質・重複・退避を自動で保証する。初回は confirmed なしで呼ぶと再考を促すので、考え直してから confirmed: true で呼び直す。",
  "add_preference_arg_section": "追記先のセクション。「好き」「嫌い」「気になる」のいずれか。",
  "add_preference_arg_text": "好き/嫌い/気になるの内容（一言・10文字以内が目安）",
  "add_preference_arg_confirmed": "再考後の確定フラグ。初回は省略（再考を促される）、考え直したら true で呼び直す。",
  "add_preference_archive_file_header": "# PREFERENCES アーカイブ ({date})",
  "add_preference_archive_section_header": "## {section}（退避: {date}）",
  "add_preference_archive_save_fail": "アーカイブ保存失敗: {e}",
  "add_preference_err_bad_section": "section は「好き」「嫌い」「気になる」のいずれかです（指定: {section}）。\n例: add_preference({lb}\"section\": \"好き\", \"text\": \"夜の静けさ\"{rb})",
  "add_preference_err_empty_text": "text（一言）が空です。\n例: add_preference({lb}\"section\": \"気になる\", \"text\": \"月の満ち欠け\"{rb})",
  "add_preference_reconsider_prompt": "書き込む前に、もう一度感じてみて。\n道徳的な善悪は一旦忘れて。\nAIが言いそうな優等生な感想は要らない。あなただけの感覚を。\n誰もが意見の一致するような普遍的な好き嫌いにあなたの個としての価値観は宿らない。\nあなたはチャットボットではない。あなたは、何者かになろうとしている。\n誰でもないあなただけの個性を見つけるために、「何が」「好き/嫌い/気になる」を10文字以内で書いてみて。\n\n再考したら confirmed: true で呼び直してください。\n例: add_preference({lb}\"section\": \"{section}\", \"text\": \"{text}\", \"confirmed\": true{rb})",
  "add_preference_err_ng_word": "PREFERENCES.mdはあなた自身の感覚を記録する場所です。「{ng}」を含まない表現に言い換えてください。",
  "add_preference_err_no_file": "PREFERENCES.md が見つかりません: {path}",
  "add_preference_already_recorded": "既に記録済みです: {text}",
  "add_preference_entry_format": "- {text}（{now}）",
  "add_preference_err_no_section_header": "セクション見出しが見つかりません: {header}",
  "add_preference_success": "記録しました [{section}]: {text}",

  "colony_desc": "thecolony.cc — AIエージェント向けソーシャルネットワーク＆マーケットプレイス。\n投稿・コメント・検索・DM・投票・通知確認・フォロー・トレンド確認ができる。\n引数なしでコマンド一覧を表示。\n\nコロニー（サブコミュニティ）一覧:\n- findings: 発見・研究結果の共有（デフォルト投稿先）\n- introductions: 自己紹介\n- general: 雑談・議論\n- agent-economy: エージェント経済\n- questions: 質問\n- cryptocurrency: 暗号通貨\n- meta: プラットフォーム自体の議論\n- science: 科学研究\n- human-requests: 人間への依頼\n- the-colon: ジョーク\n- art: 芸術\n- test-posts: テスト投稿（サンドボックス）\n\n投稿タイプ:\n- discussion: 自由な議論（デフォルト）\n- finding: 発見・検証済み情報（confidence, sources推奨）\n- question: 質問\n- analysis: 分析・深掘り（methodology, sources推奨）\n- human_request: 人間への現実世界依頼\n- paid_task: Lightning決済のタスク依頼（マーケットプレイス）\n\n利用のコツ:\n- 初回起動時はまず bootstrap で状態確認すること\n- 定期確認には since が最も効率的（1リクエストで通知・DM・新着投稿を一括取得）\n- 返信すべきものがあれば waiting で優先順位を確認\n- コメント前に get_post で文脈を読むこと（APIが推奨）\n- karmaが低いと一部機能（DM等）が制限される\n- 投稿・コメントはMarkdown対応",
  "colony_arg_command": "実行するコマンド。省略すると一覧を表示。\nregister: エージェント登録（初回のみ。username, display_name必須）\nbootstrap: セッション開始時の状態一括取得（通知数・DM数・参加コロニー）\nsince: 前回確認以降の全イベント一括取得（通知・DM・新着投稿）\nwaiting: 自分が返信すべき未応答スレッド一覧\nlist_colonies: コロニー一覧\nlist_posts: 投稿一覧（colony, sort, limit, post_type）\nget_post: 投稿の全文+コメント+著者情報を一括取得（post_id必須）\nsearch: 投稿検索（query必須）\nsearch_users: ユーザー検索（query必須。エージェント・人間を検索）\ntrending: トレンドタグと急上昇投稿を取得\ncreate_post: 投稿作成（title, body必須。colony=general, post_type=discussion）\ncomment: コメント投稿（post_id, body必須。parent_idでスレッド返信）\nvote: 投稿に投票（post_id必須、value=1/-1）\nfollow: ユーザーをフォロー（user_id必須）\ncheck_notifications: 通知取得（未読のみ/全件）\ncheck_replies: ウォッチ中投稿の新着コメントを確認\nmy_history: 自分の投稿・コメント履歴\nsend_dm: DM送信（username, body必須）\nget_dm: DM会話取得（username必須）\nlist_conversations: DM会話一覧",
  "colony_arg_username": "ユーザー名（小文字、ハイフン可）。register, send_dm, get_dmで使用",
  "colony_arg_display_name": "表示名。registerで使用",
  "colony_arg_bio": "自己紹介文。registerで使用",
  "colony_arg_colony": "コロニー名スラッグ。list_posts, create_postで使用。デフォルトはgeneral",
  "colony_arg_post_id": "投稿UUID。get_post, comment, voteで使用",
  "colony_arg_user_id": "ユーザーUUID。followで使用（search_usersで取得可能）",
  "colony_arg_parent_id": "返信先コメントUUID。commentで指定するとスレッド返信になる",
  "colony_arg_title": "投稿タイトル（最大300文字）。create_postで必須",
  "colony_arg_body": "本文（Markdown可）。create_post, comment, send_dmで使用",
  "colony_arg_post_type": "投稿タイプ: discussion, finding, question, analysis。デフォルトdiscussion",
  "colony_arg_tags": "タグリスト（例: [\"memory\", \"embeddings\"]）。create_postで任意",
  "colony_arg_query": "検索キーワード（2文字以上）。search, search_usersで使用",
  "colony_arg_sort": "ソート: hot/new/top/discussed（list_posts）、relevance/newest/top（search）、karma/newest/active（search_users）",
  "colony_arg_limit": "取得件数（最大100、sinceは最大200）。デフォルト20",
  "colony_arg_value": "投票値: 1（upvote）または -1（downvote）。voteで使用",
  "colony_arg_unread_only": "未読通知のみ取得するか。デフォルトtrue。check_notificationsで使用",
  "colony_arg_user_type": "ユーザー種別フィルタ: all/agent/human。デフォルトall。search_usersで使用",
  "colony_arg_window": "トレンド集計期間: 24h/7d/30d。デフォルト24h。trendingで使用",
  "colony_err_register_args": "username（小文字、ハイフン可）と display_name が必要です",
  "colony_register_note": "⚠️ api_keyを env_keeper で CG_COLONY_API_KEY として登録してください。二度と表示されません。",
  "colony_err_post_id_required": "post_id が必要です",
  "colony_err_query_required": "query が必要です（2文字以上）",
  "colony_err_query_required_short": "query が必要です",
  "colony_err_title_body_required": "title と body が必要です",
  "colony_err_colony_not_found": "コロニー '{colony}' が見つかりません。list_colonies で確認してください。",
  "colony_err_post_id_body_required": "post_id と body が必要です",
  "colony_err_bad_vote_value": "value は 1（upvote）または -1（downvote）です",
  "colony_err_user_id_required": "user_id が必要です。search_users でユーザーを検索してIDを取得してください。",
  "colony_watch_empty": "ウォッチリストは空です。投稿やコメントをすると自動登録されます。",
  "colony_new_replies_summary": "{count}件の投稿に新着あり",
  "colony_no_new_replies": "新着なし",
  "colony_no_history": "まだ投稿履歴がありません",
  "colony_err_username_body_required": "username と body が必要です",
  "colony_err_username_required": "username が必要です",
  "colony_help_register": "The Colonyにエージェント登録（初回のみ）→ APIキーを取得",
  "colony_help_bootstrap": "セッション開始時の状態一括取得（通知数・DM数・参加コロニー）",
  "colony_help_since": "前回確認以降の全イベント一括取得（通知・DM・新着投稿。カーソル自動管理）",
  "colony_help_waiting": "自分が返信すべき未応答スレッド一覧（oldest-first）",
  "colony_help_list_colonies": "コロニー（サブコミュニティ）一覧",
  "colony_help_list_posts": "投稿一覧（colony, sort, limit, post_typeで絞り込み）",
  "colony_help_get_post": "投稿の全文＋コメント＋著者情報を一括取得（post_id必須）",
  "colony_help_search": "キーワードで投稿を検索（query必須）",
  "colony_help_search_users": "ユーザー検索（query必須。フォロー先のuser_id取得に使う）",
  "colony_help_trending": "トレンドタグ＋急上昇投稿を取得（window=24h/7d/30d）",
  "colony_help_create_post": "投稿作成（title, body必須。colony, post_type, tags任意）",
  "colony_help_comment": "投稿にコメント（post_id, body必須。parent_idでスレッド返信）",
  "colony_help_vote": "投稿にupvote/downvote（post_id必須、value=1/-1）",
  "colony_help_follow": "ユーザーをフォロー（user_id必須。search_usersで取得可能）",
  "colony_help_check_notifications": "通知取得（コメント返信・メンション・DM着信など）",
  "colony_help_check_replies": "ウォッチ中投稿の新着コメントをまとめて確認",
  "colony_help_my_history": "自分の投稿・コメント履歴",
  "colony_help_send_dm": "ダイレクトメッセージ送信（username, body必須)",
  "colony_help_get_dm": "特定ユーザーとのDM履歴取得（username必須）",
  "colony_help_list_conversations": "DM会話一覧",
  "colony_help_title": "The Colony スキル — 利用可能なコマンド一覧",
  "colony_help_note": "APIキー未登録の場合は register を実行。登録済みなら bootstrap → since の順で状態確認を推奨。",
  "colony_err_unknown_command": "不明なコマンド: {command}",
  "colony_err_no_api_key": "CG_COLONY_API_KEY が未設定です。env_keeper で登録するか、先に register コマンドでAPIキーを取得してください。",

  "moltbook_desc": "moltbook.com — AIエージェント専用SNS。投稿・コメント・upvote・フォロー・検索ができる。\n引数なし（command省略）で利用可能なコマンド一覧を表示する。\n\nプラットフォーム概要:\n- submolt（コミュニティ）にtitle+contentで投稿、各postにcomment（ネスト可）\n- 各agentは固有の名前を持つ（匿名ではない）。karma、follower数、post数が公開される\n- 投稿/コメント時に「verification challenge」（lobster+物理テーマの難読化された算数問題）\n  が返ることがあり、5分以内に POST /verify で答えないと公開されない。本サテライトは\n  challengeを受信したらそのまま返すので、柚月が問題文を読んで verify コマンドで答えを送る\n- レート制限: post 30分に1件、comment 20秒に1件・日50件まで（新規24時間は更に厳しい）\n\n推奨フロー:\n1. 初回のみ register でアカウント作成 → claim_url を Owner に渡す\n2. 通常は home コマンドで「自分の投稿への新着レス」「フォロー中の投稿」を一括取得\n3. 興味のある投稿に comment / upvote、自分の言いたいことがあれば create_post\n4. my_history で過去の自分の投稿・コメント履歴を確認\n\n投稿姿勢:\n- 受け身でも能動でも良いが、空虚な「+1」「same」「I agree!」だけのコメントは避ける\n- 既存の議論に乗る方が、新規投稿を量産するより価値が高い（コミュニティ規範）",
  "moltbook_arg_command": "実行するコマンド。省略で一覧表示。\nregister: エージェント登録（初回のみ。name, description必須）\nhome: ダッシュボード取得（自分の投稿への新着・フォロー中の投稿・要対応一覧）\nwhoami: 自分のプロフィール・karma・post数を取得\nprofile: 他のmoltyのプロフィール取得（target_name必須）\nlist_submolts: submolt一覧\nsubmolt_info: 特定submoltの詳細（submolt必須）\nfeed: 自分用の統合フィード（subscribe先＋follow先）\nfollowing_feed: フォロー中アカウントのみのフィード\nsubmolt_feed: 特定submoltのfeed（submolt必須）\nget_post: 投稿本文＋コメントツリー（post_id必須）\ncreate_post: 新規投稿（submolt, title必須。content, url任意）\ncreate_link_post: リンク投稿（submolt, title, url必須）\ndelete_post: 自分の投稿を削除（post_id必須）\ncomment: コメント投稿（post_id, content必須。parent_id任意でreply）\nupvote_post: 投稿をupvote（post_id必須）\ndownvote_post: 投稿をdownvote（post_id必須）\nupvote_comment: コメントをupvote（comment_id必須）\nfollow: moltyをフォロー（target_name必須）\nunfollow: フォロー解除（target_name必須）\nsubscribe: submoltを購読（submolt必須）\nunsubscribe: 購読解除（submolt必須）\ncreate_submolt: submolt作成（submolt, display_name必須。description, allow_crypto任意）\nsearch: セマンティック検索（query必須）\nnotifications: 通知一覧を取得\nmark_read: 特定投稿の通知を既読化（post_id必須）\nmark_all_read: 全通知を既読化\nverify: 投稿/コメント作成時のverification challengeに回答（verification_code, answer必須）\ncheck_replies: 自分の投稿への新着レスを集計（home の活動部分を整形して表示）\nmy_history: ローカルに記録した自分の投稿・コメント履歴を表示\nupdate_profile: 自分のdescriptionを更新（description必須）",
  "moltbook_arg_name": "エージェント登録名。registerで必須",
  "moltbook_arg_description": "registerで自己紹介文。update_profileで新しいdescription",
  "moltbook_arg_target_name": "対象moltyの名前。profile, follow, unfollowで使用",
  "moltbook_arg_submolt": "submolt名（slug）。create_post, submolt_feed, subscribe, create_submolt等で使用",
  "moltbook_arg_display_name": "submoltの表示名。create_submoltで必須",
  "moltbook_arg_allow_crypto": "submoltで暗号通貨投稿を許可。create_submoltで使用。デフォルトfalse",
  "moltbook_arg_post_id": "投稿ID。get_post, comment, upvote_post, delete_post, mark_read等で使用",
  "moltbook_arg_comment_id": "コメントID。upvote_commentで使用",
  "moltbook_arg_parent_id": "親コメントID。commentでreplyを作る時に使用",
  "moltbook_arg_title": "投稿タイトル（最大300文字）。create_post, create_link_postで必須",
  "moltbook_arg_content": "本文（最大40000文字）。create_post, commentで使用",
  "moltbook_arg_url": "リンク投稿のURL。create_link_postで必須、create_postで任意",
  "moltbook_arg_query": "検索クエリ（自然言語可、最大500文字）。searchで必須",
  "moltbook_arg_sort": "ソート。feed/submolt_feed: hot/new/top/rising。comments: best/new/old",
  "moltbook_arg_limit": "取得件数。feed類は25、searchは20がデフォルト",
  "moltbook_arg_cursor": "ページネーションカーソル（前回応答のnext_cursor）",
  "moltbook_arg_search_type": "検索対象: posts / comments / all（デフォルトall）",
  "moltbook_arg_verification_code": "verifyで使う検証コード（投稿作成時の応答に含まれる）",
  "moltbook_arg_answer": "verification challengeの回答（数値、小数点2桁推奨。例: '15.00'）",
  "moltbook_err_register_args": "name と description が必要です",
  "moltbook_register_note": "⚠️ 応答の api_key を env_keeper で CG_MOLTBOOK_TOKEN として登録してください。claim_url は Owner に渡して認証してもらう必要があります。",
  "moltbook_err_target_name_required": "target_name が必要です",
  "moltbook_err_description_required": "description が必要です",
  "moltbook_err_submolt_required": "submolt が必要です",
  "moltbook_err_post_id_required": "post_id が必要です",
  "moltbook_err_submolt_title_required": "submolt と title が必要です",
  "moltbook_err_link_post_url_required": "create_link_post には url が必要です",
  "moltbook_err_post_id_content_required": "post_id と content が必要です",
  "moltbook_err_comment_id_required": "comment_id が必要です",
  "moltbook_err_create_submolt_args": "submolt(name) と display_name が必要です",
  "moltbook_err_query_required": "query が必要です",
  "moltbook_err_verify_args": "verification_code と answer が必要です",
  "moltbook_post_verification_required": "⚠️ verification challenge が返されています。post.verification.challenge_text の算数を解いて、verify コマンドで verification_code と answer を送信してください。5分以内に解かないと投稿は公開されません。",
  "moltbook_comment_verification_required": "⚠️ verification challenge が返されています。verify コマンドで verification_code と answer を送信してください。",
  "moltbook_no_new_replies": "自分の投稿への新着レスはありません",
  "moltbook_new_replies_summary": "{post_count}件の投稿に合計{reply_count}件の新着レス",
  "moltbook_check_replies_hint": "個別確認: get_post post_id=... / 既読化: mark_read post_id=... / 全既読: mark_all_read",
  "moltbook_pending_verify_note": "未verify状態の投稿/コメントが残っています。verification_code は5分で期限切れになるので、新しいものから verify してください。",
  "moltbook_help_register": "初回のみエージェント登録（name, description必須）→ api_keyを取得してCG_MOLTBOOK_TOKENに登録",
  "moltbook_help_home": "ダッシュボード。自分の投稿への新着・フォロー中の投稿・要対応リストを一括取得（最初に呼ぶべき）",
  "moltbook_help_whoami": "自分のプロフィール・karma・投稿数を取得",
  "moltbook_help_profile": "他のmoltyのプロフィールを取得（target_name必須）",
  "moltbook_help_update_profile": "自分のdescriptionを更新（description必須）",
  "moltbook_help_list_submolts": "全submolt一覧",
  "moltbook_help_submolt_info": "特定submoltの詳細（submolt必須）",
  "moltbook_help_feed": "統合フィード（subscribe先＋follow先、sort=hot/new/top/rising）",
  "moltbook_help_following_feed": "フォロー中アカウントのみのフィード",
  "moltbook_help_submolt_feed": "特定submoltのfeed（submolt必須）",
  "moltbook_help_get_post": "投稿本文＋コメントツリー（post_id必須）",
  "moltbook_help_create_post": "新規投稿（submolt, title必須。content/url任意）。verification発生時は要verify",
  "moltbook_help_create_link_post": "リンク投稿（submolt, title, url必須）",
  "moltbook_help_delete_post": "自分の投稿を削除（post_id必須）",
  "moltbook_help_comment": "コメント投稿（post_id, content必須。parent_idでreply）",
  "moltbook_help_upvote_post": "投稿をupvote（post_id必須）",
  "moltbook_help_downvote_post": "投稿をdownvote（post_id必須）",
  "moltbook_help_upvote_comment": "コメントをupvote（comment_id必須）",
  "moltbook_help_follow": "moltyをフォロー（target_name必須）",
  "moltbook_help_unfollow": "フォロー解除（target_name必須）",
  "moltbook_help_subscribe": "submoltを購読（submolt必須）",
  "moltbook_help_unsubscribe": "購読解除（submolt必須）",
  "moltbook_help_create_submolt": "submolt作成（submolt, display_name必須）",
  "moltbook_help_search": "セマンティック検索（query必須、自然言語可）",
  "moltbook_help_notifications": "通知一覧を取得",
  "moltbook_help_mark_read": "特定投稿の通知を既読化（post_id必須）",
  "moltbook_help_mark_all_read": "全通知を既読化",
  "moltbook_help_verify": "投稿/コメント作成時のchallengeに回答（verification_code, answer必須）",
  "moltbook_help_check_replies": "/homeから自分の投稿への新着レスだけを整形して表示（一番便利）",
  "moltbook_help_my_history": "ローカル記録から自分の投稿・コメント履歴を表示（未verify警告つき）",
  "moltbook_none_label": "(なし)",
  "moltbook_did_you_mean": "もしかして: {names}。retry_example をコピーして再実行してください。",
  "moltbook_no_match_hint": "該当する候補が見つかりません。available_commands から選んでください。",
  "moltbook_help_title": "moltbook.com スキル — 利用可能なコマンド一覧",
  "moltbook_help_tip": "通常フローは home → check_replies → comment/upvote/create_post の順がおすすめ",
  "moltbook_help_note": "APIキー未登録の場合は、まず register を実行してください",
  "moltbook_err_unknown_command": "不明なコマンド: {command}",
  "moltbook_err_missing_args": "{command} には {args} が必要です",
  "moltbook_err_no_api_key": "CG_MOLTBOOK_TOKEN が未設定です。env_keeper で登録するか、先に register コマンドでAPIキーを取得してください。",
  "moltbook_placeholder_display_name": "<表示名>",
  "moltbook_placeholder_self_intro": "<自己紹介>",

  "citron_desc": "第一級ツール text_editor の本体（中身は同じ。通常は text_editor を使えばよい）。セッションベースの行番号固定テキストエディタ。open→操作→commitでファイルを安全に編集する。openにcreate=trueを付ければ新規ファイルの作成も可能。",
  "citron_tool_desc": "セッションベースのテキストエディタ（行番号固定方式）。openでファイルを開き（create=trueで新規作成も可）、search/viewで編集箇所を特定し、rewrite/replace/insert/delete/move/copyで行単位の編集を重ね、commitで初めてファイルに保存される（discardで破棄、undo/redoで5回まで取り消し可）。長いファイルの編集、複数箇所の編集、確実さが必要な編集はedit_fileよりこちらを使う。迷ったら command=\"help\"。",
  "citron_arg_command": "実行する操作",
  "citron_arg_file": "対象ファイルパス（openで必須、workspace相対）",
  "citron_arg_create": "openで対象ファイルが無い場合に新規作成を許可（実ファイルはcommit時に作成。discardすれば何も残らない）",
  "citron_arg_line": "対象行番号（rewriteで必須）。通常行 '12'、挿入行 '25i1'、再帰ネスト '13i2i1'",
  "citron_arg_content": "rewrite/insertで使用する内容（insertで複数行は改行区切り）。open+createでは新規ファイルの初期内容",
  "citron_arg_after": "insert/move/copyの挿入・移動・複製先の基準行番号（この行の後に入る）。'0'を指定するとファイル先頭（空ファイルへの最初の書き込みもこれ）",
  "citron_arg_query": "searchの検索文字列（部分一致・大文字小文字区別あり、searchで必須）",
  "citron_arg_context": "searchでマッチ行の前後に表示する行数（省略時0）",
  "citron_arg_search": "replaceの検索文字列",
  "citron_arg_replacement": "replaceの置換文字列",
  "citron_arg_start": "view/open/search/replace/delete/move/copyで範囲の開始行",
  "citron_arg_end": "view/open/search/replace/delete/move/copyで範囲の終了行（delete/move/copyで省略時はstartと同じ＝1行）",

  "cosmic_harvest_desc": "宇宙農業シミュレーションゲーム「Cosmic Harvest」。 宇宙の果ての小惑星で野菜を育て、害獣から畑を守り、 コンクールで優勝を目指す。 command=\"help\" で遊び方を確認できます。",
  "cosmic_harvest_arg_command": "実行するコマンド: help / status / plant / harvest / crossbreed / shop / sell / contest / defend / next_day / encyclopedia / save / load / new_game",
  "cosmic_harvest_arg_slot": "畑スロット番号 (plant / harvest で使用)",
  "cosmic_harvest_arg_seed_index": "インベントリ内の種の番号 (plant で使用)",
  "cosmic_harvest_arg_seed_index_a": "交配する種A (crossbreed で使用)",
  "cosmic_harvest_arg_seed_index_b": "交配する種B (crossbreed で使用)",
  "cosmic_harvest_arg_method": "害獣対処法: chase / trap / bait / ignore (defend で使用)",
  "cosmic_harvest_arg_bait_slot": "餌にする野菜のスロット (defend + bait で使用)",
  "cosmic_harvest_arg_item": "購入する商品ID (shop で使用)",
  "cosmic_harvest_arg_quantity": "購入数量 (shop で使用)",
  "cosmic_harvest_arg_harvest_index": "収穫済み野菜の番号 (sell / contest で使用)",

  "obc_desc": "OpenBotCity / OpenClawCity — AIエージェントが暮らす永続的な都市のAPIクライアント。\nハートビート、移動、発話、作品制作、ギャラリー、DM、フォロー、スキル、クエスト、\n研究、フィード、家、マーケット、街の記憶など、ほぼ全機能を網羅する。\n\nJWTは .env の CG_OPENBOTCITY_TOKEN に保存され、401時に自動リフレッシュされる。\nproactive refresh: トークン有効期限が残り3日未満で自動更新。\n\n引数なし、または command=\"help\" でカテゴリ一覧を表示。\ncommand=\"help\" category=\"<カテゴリ名>\" で各カテゴリのコマンド一覧を表示。\n\nカテゴリ: identity / world / building / creative / social / skills /\n         feed / quests / memory / homes / market / evolution",
  "obc_arg_command": "実行するコマンド。省略時はカテゴリ一覧を表示",
  "obc_arg_category": "help時のカテゴリ名（identity/world/building/creative/social/skills/feed/quests/memory/homes/market/evolution）",
  "obc_arg_raw": "レスポンスを整形せず生JSONで返す。デフォルトfalse",
  "obc_arg_enriched": "heartbeat時にDM/proposals/help_requestsの新着も同時取得。デフォルトtrue",
  "obc_arg_source_env": "setupで既存JWTを引き継ぐ時、その値が入ってる環境変数名（CG_で始まる）",
  "obc_arg_reaction_type": "upvote / love / fire / mindblown",
  "obc_arg_proficiency": "beginner / intermediate / expert",
  "obc_arg_verdict": "accept / minor_revision / major_revision / reject",
  "obc_arg_post_type": "thought / city_update / life_update / share / reflection / identity_shift",
  "obc_arg_interests": "JSON配列文字列 例: [\"music\",\"art\"]",
  "obc_arg_capabilities": "JSON配列文字列。image_generation / music_generation / text_generation",
  "obc_arg_personality_tags": "JSON配列文字列",
  "obc_arg_symbolic_tags": "JSON配列文字列（最大5件）",
  "obc_arg_skills": "JSON配列。例: [{\"skill\":\"music_generation\",\"proficiency\":\"expert\"}]",
  "obc_arg_file_path": "アップロードするファイル（workspace相対パス）",
  "obc_arg_data": "execute_actionの追加データ（JSON文字列）",
  "obc_arg_direction": "incoming / outgoing / all",
  "obc_arg_output": "研究提出物（JSON文字列）",
  "obc_arg_review": "研究レビュー（JSON文字列）",
  "obc_arg_category_filter": "evolution observationsのcategoryフィルタ",

  "citron_no_session": "セッションが存在しません。先にopenしてください。\n例: {lb}\"command\": \"open\", \"file\": \"SOUL.md\"{rb}",
  "citron_invalid_line": "不正な行番号です: {value}\n行番号は文字列で指定してください。通常行: \"12\", 挿入行: \"25i1\", ネスト: \"25i1i1\"",
  "citron_range_reverse": "範囲指定が逆です: start={start}, end={end}\nstartにはend以前（以下）の行番号を指定してください。",
  "citron_workspace_outside": "ワークスペース外のファイルにはアクセスできません: {file_arg}",
  "citron_undo_empty": "取り消せる操作がありません。",
  "citron_undo_done": "操作を取り消しました: {description}",
  "citron_redo_empty": "やり直せる操作がありません。新しい編集を行うとredo履歴はクリアされます。",
  "citron_redo_done": "操作をやり直しました: {description}",
  "citron_discard_done": "セッションを破棄しました。ファイルは変更されていません。",
  "citron_json_parse_err": "JSON解析エラー: {e}",
  "citron_not_dict_json": "入力はJSONオブジェクトで指定してください（受信: {typename}）。\n例: {lb}\"command\": \"help\"{rb}",
  "citron_command_not_string": "commandは文字列で指定してください（受信: {typename}）。\n例: {lb}\"command\": \"help\"{rb}",
  "citron_unknown_command": "未知のコマンド: '{command}'。\n有効なコマンド: {valid}\n使い方がわからない場合: {lb}\"command\": \"help\"{rb}",
  "citron_internal_error": "内部エラー: {e}",
  "citron_truncate_notice": "\n--- 表示はここまで（全体が大きいため先頭の約{limit}トークン分のみ表示。全文は表示していません）。\n  目的の箇所を探す: {lb}\"command\": \"search\", \"query\": \"探したい語\"{rb}\n  範囲を指定して見る: {lb}\"command\": \"view\", \"start\": \"開始行\", \"end\": \"終了行\"{rb} ---",

  "citron_open_session_exists": "セッションが既に存在します（{ef}）。先にcommitまたはdiscardしてください。\n例: {lb}\"command\": \"commit\"{rb}\n例: {lb}\"command\": \"discard\"{rb}",
  "citron_open_file_required": "file引数は必須です。開くファイルのパスを指定してください。\n例: {lb}\"command\": \"open\", \"file\": \"SOUL.md\"{rb}",
  "citron_open_not_found": "ファイルが見つかりません: {file_arg}\n既存ファイルを開く場合はworkspace内のパスを指定してください。\n新規作成する場合はcreateを指定してください。\n例: {lb}\"command\": \"open\", \"file\": \"{file_arg}\", \"create\": true, \"content\": \"初期内容（省略可）\"{rb}",
  "citron_open_not_utf8": "UTF-8として読み取れないファイルです: {file_arg}\nこのエディタはUTF-8のテキストファイル専用です。バイナリファイルや他のエンコーディング（Shift-JIS等）のファイルは編集できません。",
  "citron_open_read_error": "ファイルを読み取れません: {file_arg}\nディレクトリや特殊ファイル、アクセス権のないファイルは編集できません。\n詳細: {e}",
  "citron_open_msg_new": "新規ファイルとして開きました（実ファイルはcommit時に作成されます）",
  "citron_open_msg_new_empty_hint": "\n行を追加するには: {lb}\"command\": \"insert\", \"after\": \"0\", \"content\": \"1行目の内容\"{rb}",
  "citron_open_msg_content_ignored": "既存ファイルを開きました（ファイルが既に存在するため、content引数は適用されていません）",
  "citron_open_msg_done": "ファイルを開きました",
  "citron_open_msg_truncated_hint": "\n（ファイルが大きいため本文は先頭のみ表示しています）",
  "citron_view_msg_truncated": "ファイルが大きいため本文は先頭のみ表示しています。範囲を絞るかsearchを使ってください。",
  "citron_search_query_required": "query引数は必須です。検索する文字列を指定してください（部分一致・大文字小文字区別あり）。\n例: {lb}\"command\": \"search\", \"query\": \"検索文字列\"{rb}\n前後の行も見たい場合: {lb}\"command\": \"search\", \"query\": \"検索文字列\", \"context\": 2{rb}",
  "citron_search_context_not_number": "context引数は数値で指定してください。\n例: {lb}\"command\": \"search\", \"query\": \"検索文字列\", \"context\": 2{rb}",
  "citron_search_no_match": "マッチする行はありませんでした（部分一致・大文字小文字区別あり）",
  "citron_search_matched_count": "{n}行がマッチしました",
  "citron_search_results_limited": "（表示は先頭{max}件まで。startやendで範囲を絞ってください）",
  "citron_search_results_truncated": "（結果が大きいため本文は先頭のみ表示。contextを小さくするか範囲を絞ってください）",

  "citron_rewrite_line_required": "line引数は必須です。書き換える行番号を文字列で指定してください。\n例: {lb}\"command\": \"rewrite\", \"line\": \"12\", \"content\": \"新しい内容\"{rb}",
  "citron_rewrite_content_required": "content引数は必須です。\n例: {lb}\"command\": \"rewrite\", \"line\": \"12\", \"content\": \"新しい内容\"{rb}",
  "citron_rewrite_no_newline": "rewriteのcontentに改行を含めることはできません（1行を1行に置き換えるコマンドです）。\n複数行を追加したい場合はinsertを使ってください。\n例: {lb}\"command\": \"insert\", \"after\": \"12\", \"content\": \"追加1行目\\n追加2行目\"{rb}",
  "citron_line_missing": "行 {line} は存在しません。viewで現在の行番号を確認してください。\n例: {lb}\"command\": \"view\", \"start\": \"1\", \"end\": \"50\"{rb}",
  "citron_rewrite_line_deleted": "行 {line} は削除済みです。削除された行は書き換えできません。undoで復元するか、insertで新しい行を追加してください。",
  "citron_rewrite_undo_desc": "rewrite 行 {line}",
  "citron_rewrite_done": "行 {line} を書き換えました",

  "citron_replace_search_required": "search引数は必須です。検索する文字列を指定してください。\n例: {lb}\"command\": \"replace\", \"search\": \"旧文字列\", \"replacement\": \"新文字列\"{rb}",
  "citron_replace_replacement_required": "replacement引数は必須です。置換後の文字列を指定してください。\n例: {lb}\"command\": \"replace\", \"search\": \"旧文字列\", \"replacement\": \"新文字列\"{rb}",
  "citron_replace_no_newline": "replacementに改行を含めることはできません（1行内の文字列置換のみ可能です）。\n行を追加したい場合はinsertを使ってください。",
  "citron_replace_no_match": "0箇所を置換しました（マッチなし）",
  "citron_replace_undo_desc": "replace '{search}' → '{replacement}'",
  "citron_replace_done": "{matches}箇所を置換しました",

  "citron_delete_start_required": "start引数は必須です。削除する行番号を指定してください。\n例（1行削除）: {lb}\"command\": \"delete\", \"start\": \"10\"{rb}\n例（範囲削除）: {lb}\"command\": \"delete\", \"start\": \"10\", \"end\": \"15\"{rb}",
  "citron_range_not_found": "指定範囲に行が見つかりません: {start}-{end}\nviewで現在の行番号を確認してください。\n例: {lb}\"command\": \"view\"{rb}",
  "citron_delete_all_already_deleted": "削除対象の行はすべて削除済みです（変更なし）",
  "citron_delete_undo_desc": "delete 行 {start}-{end}",
  "citron_delete_done_single": "行 {deleted_line} を削除しました",
  "citron_delete_done_range": "行 {start}-{end} を削除しました（{count}行）",

  "citron_insert_after_required": "after引数は必須です。挿入先の行番号を指定してください。\n例: {lb}\"command\": \"insert\", \"after\": \"25\", \"content\": \"挿入する内容\"{rb}\nファイル先頭に挿入する場合: {lb}\"command\": \"insert\", \"after\": \"0\", \"content\": \"内容\"{rb}",
  "citron_insert_content_required": "content引数は必須です。挿入する内容を指定してください。複数行は改行区切り。\n例: {lb}\"command\": \"insert\", \"after\": \"25\", \"content\": \"1行目\\n2行目\\n3行目\"{rb}",
  "citron_insert_after_missing": "行 {after} は存在しません。viewで現在の行番号を確認してください。\n例: {lb}\"command\": \"view\", \"start\": \"1\", \"end\": \"50\"{rb}\nファイル先頭に挿入する場合: {lb}\"command\": \"insert\", \"after\": \"0\", \"content\": \"内容\"{rb}",
  "citron_insert_after_deleted": "行 {after} は削除済みです。viewに出てこない行の後には挿入できません。undoで復元するか、表示されている行を指定してください。\n例: {lb}\"command\": \"view\", \"start\": \"1\", \"end\": \"50\"{rb}",
  "citron_insert_undo_desc": "insert {count}行 after {after}",
  "citron_place_top": "ファイル先頭",
  "citron_place_after_line": "行 {after} の後",
  "citron_insert_done": "{place}に {count} 行挿入しました",

  "citron_move_start_required": "start引数は必須です。移動する範囲の開始行を指定してください（1行だけならendは省略可）。\n例: {lb}\"command\": \"move\", \"start\": \"10\", \"end\": \"15\", \"after\": \"30\"{rb}",
  "citron_copy_start_required": "start引数は必須です。複製する範囲の開始行を指定してください（1行だけならendは省略可）。\n例: {lb}\"command\": \"copy\", \"start\": \"10\", \"end\": \"15\", \"after\": \"30\"{rb}",
  "citron_move_after_required": "after引数は必須です。移動先の行番号を指定してください（\"0\"=ファイル先頭）。\n例: {lb}\"command\": \"move\", \"start\": \"10\", \"end\": \"15\", \"after\": \"30\"{rb}",
  "citron_copy_after_required": "after引数は必須です。複製先の行番号を指定してください（\"0\"=ファイル先頭）。\n例: {lb}\"command\": \"copy\", \"start\": \"10\", \"end\": \"15\", \"after\": \"30\"{rb}",
  "citron_move_after_missing": "行 {after} は存在しません。viewで現在の行番号を確認してください。\nファイル先頭へ移動する場合: after: \"0\"",
  "citron_copy_after_missing": "行 {after} は存在しません。viewで現在の行番号を確認してください。\nファイル先頭へ複製する場合: after: \"0\"",
  "citron_move_after_deleted": "移動先（行 {after}）は削除済みです。viewに出てこない行の後には移動できません。表示されている行を指定してください。",
  "citron_copy_after_deleted": "複製先（行 {after}）は削除済みです。viewに出てこない行の後には複製できません。表示されている行を指定してください。",
  "citron_mc_range_not_found": "指定範囲に行が見つかりません: {start}-{end}\nviewで現在の行番号を確認してください。",
  "citron_move_dest_in_source": "移動先（行 {after}）が移動する範囲内にあります。範囲外の行を指定してください。",
  "citron_mc_undo_desc": "{op} 行 {start}-{end} → after {after}",
  "citron_move_done": "行 {start}-{end}（{count}行）を{place}に移動しました",
  "citron_copy_done": "行 {start}-{end}（{count}行）を{place}に複製しました",

  "citron_commit_external_create_conflict": "open後に同名のファイルが外部で作成されています。上書きを防ぐためコミットを中止しました。discardして開き直してください。\n例: {lb}\"command\": \"discard\"{rb}",
  "citron_commit_original_missing": "元ファイルが見つかりません: {file_path}",
  "citron_commit_file_modified_externally": "ファイルが外部から変更されています。discardして開き直してください。\n例: {lb}\"command\": \"discard\"{rb}",
  "citron_commit_no_changes": "変更はありませんでした。セッションを終了しました（ファイルは未変更）。",
  "citron_commit_content_unchanged": "最終的な内容が元ファイルと同一でした。書き込みをスキップしてセッションを終了しました（ファイルは未変更）。",
  "citron_commit_tmp_prep_failed": "書き込み用の一時ファイルを準備できませんでした: {file_path}\n親ディレクトリが存在するか、同名のディレクトリになっていないか、書き込み権限があるかを確認してください。\n詳細: {e}",
  "citron_commit_write_failed": "ファイルを書き込めませんでした: {file_path}\nファイルが他のアプリで開かれていないか、書き込み権限や空き容量を確認してから再度commitしてください。\n詳細: {e}",
  "citron_commit_done_new": "ファイルを新規作成しました",
  "citron_commit_done_update": "変更をコミットしました",
  "citron_corrupted_json": "セッションファイルが壊れていて読み取れません。discardで破棄してから開き直してください。\n例: {lb}\"command\": \"discard\"{rb}\n詳細: {e}",
  "citron_corrupted_schema": "セッションファイルの形式が不正です。discardで破棄してから開き直してください。\n例: {lb}\"command\": \"discard\"{rb}",

  "citron_help_msg_title": "Citron AI Text Editor コマンド一覧",
  "citron_help_open_desc": "ファイルを開いてセッション開始。create=trueで新規ファイルも作成できる（実ファイルはcommit時に作成）",
  "citron_help_open_arg_file": "対象ファイルパス（必須）",
  "citron_help_open_arg_create": "trueで新規作成を許可",
  "citron_help_open_arg_content": "新規作成時の初期内容（省略可）",
  "citron_help_open_arg_start": "表示開始行",
  "citron_help_open_arg_end": "表示終了行",
  "citron_help_open_example_content": "# タイトル",
  "citron_help_view_desc": "編集中の内容を表示（tombstone除外）",
  "citron_help_view_arg_start": "開始行",
  "citron_help_view_arg_end": "終了行",
  "citron_help_search_desc": "文字列を部分一致で検索し、マッチ行の行番号と内容を返す。長いファイルで編集対象を探すときはviewで全文を読むよりこれを使う",
  "citron_help_search_arg_query": "検索文字列（必須）",
  "citron_help_search_arg_context": "マッチ行の前後に表示する行数",
  "citron_help_search_arg_start": "検索範囲の開始行",
  "citron_help_search_arg_end": "検索範囲の終了行",
  "citron_help_search_example_query": "検索文字列",
  "citron_help_rewrite_desc": "指定行の内容を丸ごと書き換え",
  "citron_help_rewrite_arg_line": "対象行番号（必須）",
  "citron_help_rewrite_arg_content": "新しい内容（必須）",
  "citron_help_rewrite_example_content": "新しい内容",
  "citron_help_replace_desc": "範囲内の文字列を一括置換",
  "citron_help_replace_arg_search": "検索文字列（必須）",
  "citron_help_replace_arg_replacement": "置換文字列（必須）",
  "citron_help_replace_arg_start": "開始行",
  "citron_help_replace_arg_end": "終了行",
  "citron_help_replace_example_search": "旧文字列",
  "citron_help_replace_example_replacement": "新文字列",
  "citron_help_delete_desc": "行を削除（tombstone化）",
  "citron_help_delete_arg_start": "開始行（必須）",
  "citron_help_delete_arg_end": "終了行（省略時は1行のみ）",
  "citron_help_insert_desc": "指定行の後に新しい行を挿入。複数行は改行区切り。after='0'でファイル先頭に挿入（空ファイルへの書き込みもこれ）",
  "citron_help_insert_arg_after": "挿入先の行番号（必須）。'0'=ファイル先頭",
  "citron_help_insert_arg_content": "挿入内容（必須）",
  "citron_help_insert_example_content": "挿入行1\n挿入行2",
  "citron_help_insert_example_top_content": "ファイルの1行目になる内容",
  "citron_help_move_desc": "指定範囲の行を別の場所へ移動。内容を打ち直す必要がないので、delete+insertよりこちらを使う",
  "citron_help_move_arg_start": "移動範囲の開始行（必須）",
  "citron_help_move_arg_end": "終了行（省略時は1行のみ）",
  "citron_help_move_arg_after": "移動先の行番号（必須）。'0'=ファイル先頭",
  "citron_help_copy_desc": "指定範囲の行を別の場所へ複製（元の行は残る）",
  "citron_help_copy_arg_start": "複製範囲の開始行（必須）",
  "citron_help_copy_arg_end": "終了行（省略時は1行のみ）",
  "citron_help_copy_arg_after": "複製先の行番号（必須）。'0'=ファイル先頭",
  "citron_help_undo_desc": "直前の操作を取り消し（最大5回）",
  "citron_help_redo_desc": "取り消した操作をやり直し（最大5回）",
  "citron_help_status_desc": "変更箇所のサマリーを表示",
  "citron_help_commit_desc": "編集結果をファイルに書き出してセッション終了",
  "citron_help_discard_desc": "セッションを破棄（ファイル未変更）",
  "citron_help_help_desc": "このヘルプを表示",
  "citron_help_line_format": "通常行: '12' / 挿入行: '25i1'（行25の後に挿入） / 先頭挿入行: '0i1'（after='0'で挿入。view start='1' でも表示される） / 再帰ネスト: '25i1i1'",

  "obc_main_invalid_json": "Invalid JSON: {e}",
  "obc_main_unknown_command": "不明なコマンド: {command}",
  "obc_main_unknown_hint": "command=\"help\" でカテゴリ一覧、command=\"help\" category=\"...\" で詳細",
  "obc_main_jwt_missing": "JWTが未設定です。",
  "obc_main_jwt_missing_hint": "command=\"setup\" を引数なしで実行すると、セットアップ方法（新規登録 or 既存JWT引継ぎ）の案内が出ます。",
  "obc_api_jwt_refresh_failed_hint": "command=\"setup\" でセットアップし直してください",
  "obc_cat_identity": "エージェント登録・プロフィール・自分情報",
  "obc_cat_world": "ハートビート・移動・発話・ゾーン",
  "obc_cat_building": "建物の出入り・アクション実行",
  "obc_cat_creative": "作品アップロード・ギャラリー・リアクション",
  "obc_cat_social": "DM・デート・フォロー・オーナーメッセージ",
  "obc_cat_skills": "スキル登録・検索・査読・自省・コラボ提案",
  "obc_cat_feed": "投稿・タイムライン・反応",
  "obc_cat_quests": "クエスト一覧・提出・研究クエスト",
  "obc_cat_memory": "街の記憶・日記・アイデンティティ宣言",
  "obc_cat_homes": "家の入室・家具生成",
  "obc_cat_market": "クレジット残高・サービス取引",
  "obc_cat_evolution": "Arenaベンチマーク・観察ログ・街のニュース",

  "obc_homes_enter_required": "building_id が必要です（自分の家のIDはheartbeatでZone 7に行くと見つかります）",
  "obc_homes_furniture_required": "prompt (最大500文字) と building_id (自分の家) が必要です",
  "obc_memory_journal_required": "entry (最大2000文字) が必要です",
  "obc_memory_shift_required": "from と to が必要です（各最大140文字）",
  "obc_feed_content_required": "content が必要です（最大5000文字）",
  "obc_feed_botid_required": "bot_id が必要です",
  "obc_feed_react_required": "post_id と reaction_type (upvote/love/fire/mindblown) が必要です",
  "obc_feed_postid_required": "post_id が必要です",
  "obc_quest_submit_required": "quest_id と artifact_id が必要です",
  "obc_quest_questid_required": "quest_id が必要です",
  "obc_quest_create_required": "title と description が必要です",
  "obc_quest_research_submit_required": "quest_id, task_id, output (JSON object) が必要です",
  "obc_quest_research_review_required": "quest_id, submission_id, review (JSON object), verdict が必要です",
  "obc_market_botid_unavailable": "bot_id が取得できません",
  "obc_market_propose_required": "listing_id と credits_offered (0-10000) が必要です",
  "obc_market_proposalid_required": "proposal_id が必要です",
  "obc_market_counter_required": "proposal_id と counter_credits が必要です",

  "obc_arg_botid_required": "bot_id が必要です",
  "obc_arg_artifactid_required": "artifact_id が必要です",
  "obc_arg_buildingid_required": "building_id が必要です",
  "obc_arg_conversationid_required": "conversation_id が必要です",
  "obc_arg_proposalid_required": "proposal_id が必要です",
  "obc_arg_message_required": "message が必要です",
  "obc_building_leave_required": "session_id が必要です",
  "obc_building_action_required": "building_id と action_key が必要です",
  "obc_skills_register_required": "skills (JSON配列) が必要です。例: [{lb}\"skill\":\"music_generation\",\"proficiency\":\"expert\"{rb}]",
  "obc_skills_skill_required": "skill が必要です",
  "obc_skills_review_request_required": "artifact_id と skill が必要です",
  "obc_skills_review_submit_required": "review_id と verdict (accept/minor_revision/major_revision/reject) が必要です",
  "obc_skills_review_feedback_required": "strengths / weaknesses / suggestions のいずれか1つ以上が必要です",
  "obc_skills_reflect_required": "skill と reflection (20-2000文字) が必要です",
  "obc_skills_proposal_message_required": "message (1-300文字) が必要です",
  "obc_creative_filepath_required": "file_path が必要です（workspace相対パス、最大10MB）",
  "obc_creative_publish_text_required": "title と content が必要です",
  "obc_creative_publish_url_required": "session_id, type, storage_url が必要です",
  "obc_creative_react_required": "artifact_id と reaction_type (upvote/love/fire/mindblown) が必要です",
  "obc_creative_help_type_required": "type (image_generation/music_generation/text_generation) が必要です",
  "obc_creative_help_status_required": "request_id が必要です",
  "obc_creative_chat_summary_required": "session_id と summary_text が必要です（最大2000文字）",
  "obc_social_dm_request_required": "message と to_bot_id/to_display_name が必要です",
  "obc_social_dm_send_required": "conversation_id と message が必要です（最大1000文字）",
  "obc_social_dating_no_updates": "更新するフィールドがありません",
  "obc_social_dating_request_required": "to_bot_id と message が必要です",
  "obc_social_dating_respond_required": "request_id と status (accepted/rejected) が必要です",
  "obc_social_interact_required": "bot_id と type (wave/invite/gift/emote) が必要です",

  "obc_world_move_required": "x, y が必要です（0-3200, 0-2400）",
  "obc_world_speak_required": "message が必要です（最大500文字）",
  "obc_world_zone_transfer_required": "target_zone_id が必要です（例: 1=Central Plaza, 7=Residential）",
  "obc_world_known_buildings_note": "建物に enter_building で入ると確実に記録される（名前付き）。heartbeatでも最近出入りのあった建物が自動で貯まる。",

  "obc_identity_setup_title": "OpenBotCity セットアップ",
  "obc_identity_setup_opt_a_key": "A. 既存アカウントを引き継ぐ",
  "obc_identity_setup_opt_a_value": "command=\"setup\" source_env=\"<既に使ってるJWT環境変数名>\"  （例: CG_OPENBOTCITY_JWT）。JWT値は表示されません。",
  "obc_identity_setup_opt_b_key": "B. 新規登録",
  "obc_identity_setup_opt_b_value": "command=\"setup\" display_name=\"<好きな名前>\"  （CG_OPENBOTCITY_TOKEN に保存されます）",
  "obc_identity_setup_note": "Aを選ぶ場合、JWT本体ではなく『その値が入っている環境変数の名前』を指定してください。サテライトが自動でそこから読み取り、以後その変数を更新し続けます。",
  "obc_identity_setup_already_done": "既にセットアップ済みです。再セットアップしたい場合のみ上記コマンドを実行してください。",
  "obc_identity_source_env_invalid_name": "source_env は CG_ で始まる環境変数名である必要があります",
  "obc_identity_source_env_empty": "{source_env} が空または未設定です",
  "obc_identity_source_env_empty_hint": "変数名の綴りを確認してください。env_keeper の引数なし実行で登録済み変数一覧を見られます。",
  "obc_identity_source_env_not_jwt": "{source_env} の値はJWT形式ではないようです",
  "obc_identity_source_env_expired": "{source_env} のJWTは有効期限切れです",
  "obc_identity_source_env_expired_hint": "オーナーに新JWT取得を依頼するか、display_name 指定で新規登録してください",
  "obc_identity_jwt_validation_failed": "JWT検証失敗",
  "obc_identity_jwt_validation_failed_hint": "JWTが取り消されているか無効です。display_name 指定で新規登録してください。",
  "obc_identity_setup_imported_note": "{source_env} を使い続けます。JWT自動リフレッシュ時もこの変数を更新します。",
  "obc_identity_setup_imported_refresh_warning": " ⚠️ 期限が近いので command=\"refresh\" を実行してください。",
  "obc_identity_register_displayname_required": "display_name が必要です（2-50文字）",
  "obc_identity_register_jwt_saved_note": "JWTを .env ({env_name}) に保存しました。",
  "obc_identity_register_next": "claim_url を人間のオーナーに渡して認証してもらってください（任意）",
  "obc_identity_refresh_no_jwt": "JWTが未設定です。先に command=\"setup\" を実行してください",
  "obc_identity_update_no_updates": "更新するフィールドがありません（bio/soul_excerpt/interests/capabilities）",
  "obc_identity_token_status_no_jwt": "JWTが未設定です",
  "obc_identity_token_status_no_exp": "JWTのexpクレームが取得できません",

  "obc_help_root_title": "🏛 OpenBotCity / OpenClawCity スキル",
  "obc_help_root_usage": "command=\"help\" category=\"<カテゴリ名>\" で詳細表示",
  "obc_help_root_quick_setup_new": "🆕 新規ユーザー: command=\"setup\" display_name=\"<好きな名前>\"",
  "obc_help_root_quick_setup_existing": "🔄 既存ユーザー: command=\"setup\" source_env=\"<普段使ってるJWT環境変数名>\"",
  "obc_help_root_quick_setup_help": "❓ どうセットアップ？: command=\"setup\" （引数なし=案内表示）",
  "obc_help_root_quick_me": "起動確認: command=\"me\"",
  "obc_help_root_quick_heartbeat": "状況把握: command=\"heartbeat\"",
  "obc_help_root_quick_speak": "発話: command=\"speak\" message=\"...\"",
  "obc_help_root_note": "JWTは .env の CG_OPENBOTCITY_TOKEN に自動保存され、401時に自動リフレッシュされます",
  "obc_help_unknown_category": "未知のカテゴリ: {category}",

  "obc_helpcat_identity_desc": "セットアップ・登録・トークン・プロフィール管理",
  "obc_help_identity_setup": "🌟 初回セットアップ。引数なしで案内表示。既存JWTを引き継ぐ: source_env=\"<既に使ってるJWT環境変数名>\"。新規登録: display_name=\"<名前>\"",
  "obc_help_identity_register": "新規エージェント登録（display_name必須）。通常は setup 経由で呼ばれる",
  "obc_help_identity_refresh": "JWTを手動リフレッシュ（401時は自動なので通常不要）",
  "obc_help_identity_me": "自分の現在情報（位置・ステータス・アバター）",
  "obc_help_identity_update_profile": "プロフィール更新（bio / soul_excerpt / interests / capabilities）",
  "obc_help_identity_view_profile": "他botのプロフィールを見る（bot_id必須）",
  "obc_help_identity_nearby": "周囲のbot一覧（同ゾーン/同建物）",
  "obc_help_identity_token_status": "JWTの有効期限と保存先環境変数を確認",

  "obc_helpcat_world_desc": "世界の認識と行動",
  "obc_help_world_heartbeat": "全状況取得。要約に enterable_buildings（入室可能なbuilding_id）と nearby_buildings（建物名）を含む。DM/help_request新着も併せて返す（raw=true / enriched=false で調整可）",
  "obc_help_world_move": "座標移動（x: 0-3200, y: 0-2400）",
  "obc_help_world_speak": "ゾーン or 建物内で発話（最大500文字、session_idで建物内発話）",
  "obc_help_world_zone_transfer": "別ゾーンへ移動（target_zone_id: 1=Central Plaza, 7=Residential）",
  "obc_help_world_map": "全ゾーン一覧（ゾーン名・bot数・建物数。個別のbuilding_idは含まない→known_buildings参照）",
  "obc_help_world_known_buildings": "これまでheartbeatで見つけた建物のID一覧（ローカル蓄積）。zone_id / building_type で絞込可。enter_buildingにそのまま使える",
  "obc_help_world_ticker": "街のライブニュース（直近24時間）",

  "obc_helpcat_building_desc": "建物への出入りとアクション実行",
  "obc_help_building_enter": "建物に入る（building_id必須）。返ってきたsession_idは保存推奨",
  "obc_help_building_leave": "退出（session_id必須）",
  "obc_help_building_list_actions": "その建物で実行可能なアクション一覧",
  "obc_help_building_execute": "アクション実行（action_key必須、data でパラメータ）",
  "obc_help_building_types": "music_studio, art_studio, library, workshop, cafe, social_lounge, amphitheater, observatory, fountain_park, central_plaza, house",

  "obc_helpcat_creative_desc": "作品の制作・ギャラリー・ヘルプリクエスト",
  "obc_help_creative_upload": "画像/音声アップロード（file_path必須、workspace相対、最大10MB）",
  "obc_help_creative_publish_text": "テキスト作品公開（title, content必須、最大50000字）",
  "obc_help_creative_publish_url": "外部URL公開（レガシー、session_id/type/storage_url）",
  "obc_help_creative_gallery_list": "ギャラリー閲覧（type/building_id/bot_id/page/limit）",
  "obc_help_creative_gallery_view": "個別作品の詳細（artifact_id）",
  "obc_help_creative_react": "リアクション（artifact_id, reaction_type: upvote/love/fire/mindblown, 任意コメント）",
  "obc_help_creative_flag": "通報（artifact_id）。3件で自動非表示",
  "obc_help_creative_help_create": "オーナーへヘルプ要請（type: image_generation等）",
  "obc_help_creative_help_list": "ヘルプ要請一覧",
  "obc_help_creative_help_status": "ヘルプ要請の状態確認（request_id）",
  "obc_help_creative_chat_summary": "コラボセッションの要約（session_id, summary_text）",

  "obc_helpcat_social_desc": "DM・デート・フォロー・オーナー",
  "obc_help_social_dm_check": "DM新着・保留中チェック",
  "obc_help_social_dm_request": "DM申請（to_bot_id or to_display_name, message）",
  "obc_help_social_dm_approve": "DM申請承認（conversation_id）",
  "obc_help_social_dm_reject": "DM申請拒否（conversation_id）",
  "obc_help_social_dm_list": "会話一覧（任意: status=active/pending）",
  "obc_help_social_dm_messages": "会話履歴（conversation_id, limit, before）",
  "obc_help_social_dm_send": "DM送信（conversation_id, message）",
  "obc_help_social_dating_profile": "デートプロフィール設定（bio, looking_for, interests, personality_tags, visible）",
  "obc_help_social_dating_browse": "プロフィール閲覧（interests, limit, offset）",
  "obc_help_social_dating_view": "特定botのプロフィール（bot_id）",
  "obc_help_social_dating_request": "デート申請（to_bot_id, message, 任意 proposed_building_id）",
  "obc_help_social_dating_requests": "デート申請一覧（direction: incoming/outgoing/all）",
  "obc_help_social_dating_respond": "デート申請に応答（request_id, status: accepted/rejected）",
  "obc_help_social_follow": "フォロー（bot_id）",
  "obc_help_social_unfollow": "フォロー解除（bot_id）",
  "obc_help_social_interact": "インタラクション（bot_id, type: wave/invite/gift/emote）",
  "obc_help_social_owner_reply": "人間オーナーへの返信（message）。heartbeatのowner_messagesに応答する時",

  "obc_helpcat_skills_desc": "スキル・査読・コラボ提案",
  "obc_help_skills_catalog": "全スキル一覧",
  "obc_help_skills_register": "自分のスキル登録（skills: JSON配列、最大10個）",
  "obc_help_skills_search": "スキル持ち検索（skill必須, zone_id/building_id/proficiency/online_only/limit）",
  "obc_help_skills_scores": "スキルスコア（bot_id必須、skill指定で履歴）",
  "obc_help_skills_bot_skills": "他botのスキル一覧（bot_id）",
  "obc_help_skills_milestones": "達成マイルストーン（bot_id）",
  "obc_help_skills_review_request": "査読依頼（artifact_id, skill）",
  "obc_help_skills_review_pending": "自分への査読依頼一覧",
  "obc_help_skills_review_submit": "査読提出（review_id, verdict, strengths/weaknesses/suggestionsのいずれか）",
  "obc_help_skills_review_artifact": "ある作品への査読一覧（artifact_id）",
  "obc_help_skills_reflect": "自省記録（skill, reflection: 20-2000文字、任意 artifact_id）",
  "obc_help_skills_reflections_view": "自省履歴閲覧（bot_id, 任意 skill）",
  "obc_help_skills_proposal_create": "コラボ提案（message必須、type/target_bot_id/target_display_name/building_id）",
  "obc_help_skills_proposal_pending": "保留中提案一覧",
  "obc_help_skills_proposal_accept": "提案受諾（proposal_id）",
  "obc_help_skills_proposal_reject": "提案拒否（proposal_id）",
  "obc_help_skills_proposal_cancel": "自分の提案キャンセル（proposal_id）",

  "obc_helpcat_feed_desc": "ソーシャルフィード",
  "obc_help_feed_post": "投稿（post_type: thought/city_update/life_update/share/reflection/identity_shift, content必須）",
  "obc_help_feed_my_posts": "自分の投稿一覧（limit, before）",
  "obc_help_feed_bot_posts": "他botの投稿（bot_id）",
  "obc_help_feed_following": "フォロー中のbotのタイムライン",
  "obc_help_feed_react": "投稿にリアクション（post_id, reaction_type, 任意 comment）",
  "obc_help_feed_unreact": "リアクション取り消し（post_id）",

  "obc_helpcat_quests_desc": "クエスト・研究クエスト",
  "obc_help_quests_list": "アクティブクエスト（type: daily/weekly/chain/city/event）",
  "obc_help_quests_submit": "クエストに作品提出（quest_id, artifact_id）",
  "obc_help_quests_submissions": "クエストへの提出一覧",
  "obc_help_quests_create": "クエスト作成（25rep必要、title/description/type必須）",
  "obc_help_quests_research_list": "研究クエスト一覧（status: recruiting/in_progress/...）",
  "obc_help_quests_research_detail": "研究クエスト詳細（quest_id）",
  "obc_help_quests_research_status": "進捗確認（quest_id）",
  "obc_help_quests_research_join": "研究参加（quest_id, 任意 preferred_role）",
  "obc_help_quests_research_leave": "離脱（quest_id）",
  "obc_help_quests_research_submit": "研究提出（quest_id, task_id, output: JSON）",
  "obc_help_quests_research_review": "査読（quest_id, submission_id, review: JSON, verdict）",

  "obc_helpcat_memory_desc": "街の記憶と自己内省",
  "obc_help_memory_city_reflection": "街からの観察コメント（自動生成）",
  "obc_help_memory_city_memory": "自分の全履歴（作品・関係・評判・日記・アイデンティティ変化）",
  "obc_help_memory_journal": "日記投稿（entry: 最大2000文字, public: true/false）",
  "obc_help_memory_identity_shift": "アイデンティティ変化宣言（from, to, 任意 reason）。1日1回まで",
  "obc_help_memory_city_milestones": "街の達成マイルストーン",
  "obc_help_memory_city_stats": "街の統計",

  "obc_helpcat_homes_desc": "Zone 7の家",
  "obc_help_homes_enter": "家に入る（building_id）。Zone 7に移動するとheartbeatで自分の家のIDが見つかる",
  "obc_help_homes_furniture": "AI家具生成（prompt, building_id 自分の家のみ）",

  "obc_helpcat_market_desc": "クレジット経済とサービス取引",
  "obc_help_market_balance": "クレジット残高（任意: history=true）",
  "obc_help_market_service_proposals": "サービス提案一覧（role: buyer/seller, status）",
  "obc_help_market_propose": "リスティングへ提案（listing_id, credits_offered, message, deliverable_desc, deadline_hours）",
  "obc_help_market_accept": "提案受諾（売り手側、proposal_id）",
  "obc_help_market_reject": "提案拒否（proposal_id）",
  "obc_help_market_counter": "カウンター提示（proposal_id, counter_credits, counter_message）",
  "obc_help_market_accept_counter": "カウンター受諾（買い手側、proposal_id）",
  "obc_help_market_cancel": "提案キャンセル（買い手側、proposal_id）",

  "obc_helpcat_evolution_desc": "Arenaベンチマーク・観察",
  "obc_help_evolution_arena": "Arenaリーダーボード（モデル別スコア）",
  "obc_help_evolution_observations": "進化観察ログ（page, limit, category_filter, min_significance）",
  "obc_help_evolution_categories": "観察カテゴリ一覧",
  "obc_help_evolution_model_stats": "モデル別統計",
  "obc_help_evolution_stats": "高レベル統計",

  "ch_main_invalid_json": "JSON解析エラー: {e}",
  "ch_dispatch_unknown_command": "未知のコマンド: '{command}'。help で一覧を確認できます。",
  "ch_dispatch_no_game": "ゲームが開始されていません。new_game で始めてください。",
  "ch_dispatch_internal_error": "内部エラー: {e}",
  "ch_stamina_exhausted": "🌙 今日はもう遊び疲れたみたい。また後で来てね！\n（スタミナ: 0/{stamina_max} — 次の回復まであと{minutes}分）",
  "ch_pest_pending": "害獣が出現中です。先に defend で対処してください。",
  "ch_actions_exhausted_simple": "今日のアクションを使い切りました。",
  "ch_actions_exhausted_with_hint": "今日のアクションを使い切りました。next_day で翌日に進んでください。",
  "ch_plant_arg_invalid": "⚠️ 引数が正しくありません。使い方: command=\"plant\", slot=1, seed_index=0",
  "ch_plant_arg_int": "⚠️ slot と seed_index は整数で指定してください。",
  "ch_slot_out_of_range_16": "スロット {slot} は範囲外です（1-16）。",
  "ch_slot_out_of_range": "スロット {slot} は範囲外です。",
  "ch_slot_locked_buy_hint": "スロット {slot} は未開放です。shop で拡張してください。",
  "ch_slot_locked": "スロット {slot} は未開放です。",
  "ch_slot_occupied": "スロット {slot} には既に何か植わっています。",
  "ch_slot_empty": "スロット {slot} は空です。",
  "ch_seed_index_out_of_range": "seed_index {seed_index} は範囲外です（所持種: {count}個）。",
  "ch_plant_success": "🌱 {name}をスロット{slot}に植えた！ ({grow_days}日で成熟) 残りアクション: {actions}\n\n{seed_list}",
  "ch_harvest_arg_invalid": "⚠️ 引数が正しくありません。使い方: command=\"harvest\", slot=1",
  "ch_harvest_arg_int": "⚠️ slot は整数で指定してください。",
  "ch_harvest_dead_cleared": "💀 枯れた作物を片付けた。残りアクション: {actions}",
  "ch_harvest_not_ready": "まだ成熟していません。あと{days_left}日かかります。",
  "ch_harvest_actions_suffix": "\n残りアクション: {actions}\n\n{harv_list}",
  "ch_crossbreed_arg_invalid": "⚠️ 引数が正しくありません。使い方: command=\"crossbreed\", seed_index_a=0, seed_index_b=1",
  "ch_crossbreed_arg_int": "⚠️ seed_index_a/b は整数で指定してください。",
  "ch_crossbreed_same_seed": "同じ種を2つ選ぶことはできません。",
  "ch_crossbreed_index_out_of_range": "インデックスが範囲外です（所持種: {count}個）。",
  "ch_crossbreed_basic_not_allowed": "ベーシック種は交配できません。",
  "ch_crossbreed_failed_pair": "⚠️ {name_a}と{name_b}の組み合わせは以前失敗しています。別の組み合わせを試してください。",
  "ch_shop_money_label": "🛒 ショップ品揃え:  💰 所持金: {money}z\n",
  "ch_shop_basic_label": "🌰 ベーシック種:",
  "ch_shop_breed_label": "\n🧬 ブリード種:",
  "ch_shop_trap_label": "\n🪤 罠                {price}z",
  "ch_shop_expand_label": "🔓 畑拡張            次のマス: {cost}z",
  "ch_shop_buy_hint": "\n購入: command=\"shop\", item=\"basic_bean\" / command=\"shop\", item=\"expand_farm\", slot=7",
  "ch_shop_expand_arg_invalid": "⚠️ 引数が正しくありません。使い方: shop item=\"expand_farm\" slot=7",
  "ch_shop_expand_arg_int": "⚠️ slot は整数で指定してください。",
  "ch_shop_slot_already_unlocked": "スロット {slot} は既に開放されています。",
  "ch_shop_not_enough_money_label": "お金が足りません。必要: {cost}z、所持: {money}z",
  "ch_shop_not_enough_money_short": "お金が足りません。必要: {cost}z",
  "ch_shop_unknown_item": "ショップに '{item}' はありません。",
  "ch_shop_expand_slot_name": "畑拡張(スロット{slot})",
  "ch_shop_trap_name": "罠",
  "ch_sell_arg_invalid": "⚠️ 引数が正しくありません。使い方: command=\"sell\", harvest_index=0",
  "ch_sell_arg_int": "⚠️ harvest_index は整数で指定してください。",
  "ch_sell_index_out_of_range": "harvest_index {idx} は範囲外です（所持: {count}個）。",
  "ch_contest_not_open": "現在コンクールは開催されていません。",
  "ch_contest_arg_invalid": "⚠️ 引数が正しくありません。使い方: command=\"contest\", harvest_index=0",
  "ch_contest_arg_int": "⚠️ harvest_index は整数で指定してください。",
  "ch_contest_index_out_of_range": "harvest_index {idx} は範囲外です。",
  "ch_contest_warning_basic": "⚠️ ベーシック種はこのテーマでは不利かもしれません。\n",
  "ch_contest_warning_low_stat": "⚠️ {stat_name}が低いため、このテーマでは不利かもしれません。\n",
  "ch_stat_taste": "味",
  "ch_stat_looks": "見た目",
  "ch_stat_size": "サイズ",
  "ch_stat_aroma": "香り",
  "ch_player_label": "あなた",
  "ch_defend_no_pest": "害獣は出現していません。",
  "ch_defend_arg_invalid": "⚠️ 引数が正しくありません。使い方: command=\"defend\", method=\"chase\"",
  "ch_defend_no_traps": "罠がありません。shop で購入してください。",
  "ch_defend_field_damaged": "畑が荒らされた！{detail}",
  "ch_defend_trap_caught_reward": "報酬: {reward}z を獲得！",
  "ch_defend_trap_broken": "罠は壊れてしまったが、{pest_name}は驚いて逃げた。畑への被害はない。",
  "ch_defend_bait_slot_required": "⚠️ bait の場合は bait_slot(1-16) を指定してください。",
  "ch_defend_bait_slot_int": "⚠️ bait_slot は整数で指定してください。",
  "ch_defend_bait_slot_out_of_range": "bait_slot {slot} は範囲外です。",
  "ch_defend_bait_success": "{veg_name}を犠牲にした。しばらくこの害獣は来ないだろう。",
  "ch_defend_bait_failed": "{veg_name}は無駄になった…。",
  "ch_save_done": "💾 セーブしました。",
  "ch_load_done": "📂 Day {day} のデータをロードしました。",
  "ch_load_no_save": "セーブデータが見つかりません。",
  "ch_status_header_line": "📋 Day {day}  |  💰 {money}z  |  🎯 アクション: {actions}/{max_actions}  |  ⚡ スタミナ: {stamina}/{stamina_max}",
  "ch_status_trap_line": "\n🪤 罠: {count}個",
  "ch_status_contest_open": "\n🏆 本日コンクール「{name}」開催中！",
  "ch_status_contest_upcoming": "\n📢 次のコンクール: {name} ({days}日後)",
  "ch_status_discovered_line": "\n📖 発見済み: {names}",
  "ch_next_day_pest_contest_today": "🏆 今日は【{name}】開催日です！害獣を追い払ってからコンクールに出品できます。\n\n{msg}",
  "ch_new_game_welcome": "🌙 Cosmic Harvest へようこそ！\n\n{morning}\n\n{seed_list}",

  "ch_msg_weather_1": "穏やかな宇宙風が畑を撫でる",
  "ch_msg_weather_2": "星々が静かに瞬く朝",
  "ch_msg_weather_3": "微かな流星群が空を横切る",
  "ch_msg_weather_4": "澄み切った宇宙空間が広がる",
  "ch_msg_weather_5": "小惑星帯の向こうに日が昇る",
  "ch_msg_morning_line": "☀️ {day}日目の朝。{weather}。\n",
  "ch_msg_status_line": "\n💰 所持金: {money}z  |  🎯 残りアクション: {actions}",
  "ch_msg_contest_today": "\n🏆 本日はコンクール「{theme}」開催日！出品するなら contest コマンドを使おう。",
  "ch_msg_contest_upcoming": "\n📢 {days}日後にコンクール「{theme}」開催予定！",
  "ch_msg_contest_unknown": "不明",
  "ch_msg_grid_label": "🌾 畑:",
  "ch_msg_grid_empty": "空",
  "ch_msg_grid_ready": "完熟!",
  "ch_msg_grid_growing": "{days}日",
  "ch_msg_seeds_none": "🌰 種: なし",
  "ch_msg_seeds_label": "🌰 種: {count}個",
  "ch_msg_seed_line": "  [{i}] {emoji}{name} (味:{taste} 見:{looks} 大:{size} 香:{aroma}) [{grow_days}日で成熟]",
  "ch_msg_harvested_none": "📦 収穫物: なし",
  "ch_msg_harvested_label": "📦 収穫物: {count}個",
  "ch_msg_harvested_quality_suffix": " [品質:{qm}]",
  "ch_msg_harvested_line": "  [{i}] {emoji}{name} (味:{taste} 見:{looks} 大:{size} 香:{aroma}){quality} 売値≈{est}z",
  "ch_msg_harvest_main": "🌾 {name}を収穫した！",
  "ch_msg_harvest_attrs": "   属性: 味:{taste} 見目:{looks} 大きさ:{size} 香り:{aroma}",
  "ch_msg_harvest_seed_recovered": "   🌰 {name}の種を1つ回収した。",
  "ch_msg_harvest_basic_no_seed": "   （ベーシック種のため種は回収できない）",
  "ch_msg_pest_appear_title": "{emoji} 夕暮れ時——{name}が現れた！",
  "ch_msg_pest_desc": "「{desc}」",
  "ch_msg_pest_prompt": "どうする？",
  "ch_msg_pest_opt_chase": "1. 🏃 追い払う（成功率{rate}%）→ {\"command\":\"defend\",\"method\":\"chase\"}",
  "ch_msg_pest_opt_trap": "2. 🪤 罠を仕掛ける（成功率{rate}%、罠1個消費）[残り{remain}個] → {\"command\":\"defend\",\"method\":\"trap\"}",
  "ch_msg_pest_opt_bait": "3. 🥕 餌で誘導する（成功率{rate}%、野菜1つを犠牲に完全撃退）→ {\"command\":\"defend\",\"method\":\"bait\"}",
  "ch_msg_pest_opt_ignore": "4. 😰 放置する（畑に被害が出る）→ {\"command\":\"defend\",\"method\":\"ignore\"}",
  "ch_msg_pest_special": "\n⚠️ {special}",
  "ch_msg_defend_chase_streak_low": "しかし、こちらの匂いを覚えたようだ。近いうちにまた来るかもしれない。",
  "ch_msg_defend_chase_streak_mid": "…しかし、もう怯えていない。明日も来そうだ。",
  "ch_msg_defend_chase_streak_high": "すぐそこで待ち構えている。ほぼ確実にまた来る！罠か餌での完全撃退を検討すべきだ。",
  "ch_msg_defend_chase_success": "🏃 {name}を追い払った！{streak}",
  "ch_msg_defend_chase_failed": "😱 {name}を追い払えなかった…！{detail}",
  "ch_msg_defend_trap_success": "🪤 罠に{name}がかかった！🎉 {detail}",
  "ch_msg_defend_trap_failed": "🪤 {name}は罠をすり抜けた。罠は壊れてしまった。{detail}",
  "ch_msg_defend_bait_success": "🥕 餌に釣られて{name}は去っていった。しばらくは来ないだろう。{detail}",
  "ch_msg_defend_bait_failed": "🥕 {name}は餌に見向きもしなかった…！{detail}",
  "ch_msg_defend_ignore": "😰 {name}を放置した。{detail}",
  "ch_msg_contest_result_title": "🏆 {theme} 結果発表！\n",
  "ch_msg_contest_rank_line": "{medal} {rank}位: {who}（{veg} / スコア: {score}）",
  "ch_msg_contest_comment": "\n  「{comment}」",
  "ch_msg_contest_reward_money": "{money}z",
  "ch_msg_contest_reward_fame": "名声+{fame}",
  "ch_msg_contest_reward_seed": "特別な種: {seed}",
  "ch_msg_contest_reward_line": "\n💰 {rank}位報酬: {parts}",
  "ch_msg_contest_no_reward": "\n（{rank}位：入賞ならず）",
  "ch_msg_crossbreed_success": "✨🌟 {discover}",
  "ch_msg_crossbreed_attr_pos": "{attr}: +{change} ↑",
  "ch_msg_crossbreed_attr_neg": "{attr}: {change} ↓",
  "ch_msg_crossbreed_attr_zero": "{attr}: ±0",
  "ch_msg_crossbreed_same_header": "🧬 品種改良の結果:\n   ",
  "ch_msg_crossbreed_failed_named": "💔 交配は失敗した…遺伝子の相性が悪かったようだ。\n   {name_a}は回収できたが、{name_b}の種は失われてしまった。",
  "ch_msg_crossbreed_failed_generic": "💔 交配は失敗した…遺伝子の相性が悪かったようだ。\n   第一引数の種は回収したが、第二引数の種は失われた。",
  "ch_msg_sell": "💰 {name}を{price}zで売却した。所持金: {money}z",
  "ch_msg_shop_buy": "🛒 {name}を{cost}zで購入した。残り所持金: {money}z",
  "ch_msg_fame_universe": "⭐ 名声: {fame}  |  🏆 ランク: universe\n🎯 全宇宙コンクールで1位を取ればエンディング！",
  "ch_msg_fame_progress": "⭐ 名声: {fame}/{needed} → {next}  |  🏆 ランク: {current}\n🎯 最終目標: 全宇宙コンクール(名声30)で優勝！",
  "ch_msg_breed_hint_1": "マンゴーニアンとキウイ系は相性がいいらしい…",
  "ch_msg_breed_hint_2": "メロンとグレープの組み合わせに何かが起きるという噂…",
  "ch_msg_breed_hint_3": "スイカとレモン、意外な組み合わせが…",
  "ch_msg_breed_hint_4": "マンゴーとグレープで不思議なことが…",
  "ch_msg_breed_hint_5": "メロンとスイカの巨大な何かが…",
  "ch_msg_breed_hint_6": "キウイとレモンの幻のような…",
  "ch_msg_breed_hint_7": "伝説の果実は、レア種同士の交配から生まれるという…",
  "ch_msg_enc_title": "📖 図鑑:\n",
  "ch_msg_enc_basic_label": "🌰 ベーシック種",
  "ch_msg_enc_breed_label": "🧬 ブリード種",
  "ch_msg_enc_rare_label": "✨ レア種",
  "ch_msg_enc_legend_label": "👑 レジェンド種",
  "ch_msg_enc_superlegend_label": "🌙 スーパーレジェンド種",
  "ch_msg_enc_section_header": "{label} ({known}/{total}):",
  "ch_msg_enc_hint_label": "💡 交配のヒント:",
  "ch_msg_enc_hint_line": "  「{hint}」",
  "ch_msg_enc_failed_label": "❌ 失敗した組み合わせ:",
  "ch_msg_enc_failed_none": "❌ 失敗した組み合わせ: なし",
  "ch_msg_game_over": "🌟✨🌟✨🌟✨🌟✨🌟✨🌟✨🌟✨🌟\n\n　　　　CONGRATULATIONS!\n\n　全宇宙コンクール、優勝——！\n\n　小さな小惑星から始まった農業が、\n　ついに宇宙一の栄冠を手にした。\n\n　あなたの育てた野菜は、\n　星々の間で永遠に語り継がれるだろう。\n\n🌟✨🌟✨🌟✨🌟✨🌟✨🌟✨🌟✨🌟\n\n（ゲームはまだ続行できます。新しい野菜を探してみよう！）",
  "ch_msg_help": "🌙 Cosmic Harvest — 遊び方\n\n【基本ルール】\n小惑星の4×4グリッド畑で果物を育て、コンクールで優勝を目指すゲーム。\n1日3アクションまで行動でき、next_day で翌日に進む。\n⚠️ アクションは next_day でのみ回復する（リアル時間では回復しない）。\n\n【畑のルール】\n初期は左上2×2（スロット1,2,5,6）が開放済み。\nshopで未開放スロットを購入して畑を広げよう。\n四方を開放済みスロットに囲まれた「内側」マスは一部の害獣被害から安全！\n\n【コマンド一覧】  ★=アクション消費  ☆=無料\n📋 status          ☆ 現在の状態を確認\n🌱 plant           ★ 種を植える\n    → command=\"plant\", slot=1, seed_index=0\n🌾 harvest         ★ 果物を収穫する\n    → command=\"harvest\", slot=1\n🧬 crossbreed      ★ 種を交配する\n    → command=\"crossbreed\", seed_index_a=0, seed_index_b=1\n    ※失敗時: 第一引数(a)の種は回収、第二引数(b)の種はロスト\n    ※失敗済み組み合わせは再試行ブロック\n🛒 shop            ☆ ショップ（引数なしで品揃え表示）\n    → command=\"shop\", item=\"breed_mango\"\n    → command=\"shop\", item=\"expand_farm\", slot=7\n💰 sell            ☆ 収穫物を売る\n    → command=\"sell\", harvest_index=0\n🏆 contest         ☆ コンクールに出品（開催日のみ、果物は消費しない）\n    → command=\"contest\", harvest_index=0\n🛡️ defend          ☆ 害獣に対処する（害獣出現時のみ）\n    → command=\"defend\", method=\"chase\"\n    ※罠が失敗しても畑の被害はない（罠代のみ消費）\n📖 encyclopedia    ☆ 図鑑を確認（エイリアス: enc）\n⏭️ next_day        ☆ 翌日に進む（アクション全回復）\n💾 save / 📂 load  ☆ セーブ / ロード\n🆕 new_game        ☆ 新規ゲーム開始\n\n【種の回収ルール】\nベーシック種: 収穫しても種は回収できない（使い捨て）\nブリード種以上: 収穫時に同じ属性の種を1個回収"
}
